{"confirmed": true, "home": {"players": [{"player": {"name": "Miloje Preković", "slug": "miloje-prekovic", "shortName": "M. Preković", "position": "G", "jerseyNumber": "12", "height": 193, "userCount": 31, "gender": "M", "country": {"alpha2": "RS", "alpha3": "SRB", "name": "Serbia", "slug": "serbia"}, "id": 795839, "marketValueCurrency": "EUR", "dateOfBirthTimestamp": 676252800, "proposedMarketValueRaw": {"value": 52000, "currency": "EUR"}, "fieldTranslations": {"nameTranslation": {"ar": "ميلوجي بريكوفيتش"}, "shortNameTranslation": {"ar": "م. بريكوفيتش"}}}, "teamId": 25736, "shirtNumber": 12, "jerseyNumber": "12", "position": "G", "substitute": false, "statistics": {"totalPass": 27, "accuratePass": 19, "totalLongBalls": 13, "accurateLongBalls": 5, "goalAssist": 0, "accurateOwnHalfPasses": 18, "totalOwnHalfPasses": 20, "accurateOppositionHalfPasses": 1, "totalOppositionHalfPasses": 7, "totalClearance": 1, "ballRecovery": 6, "savedShotsFromInsideTheBox": 2, "penaltySave": 1, "penaltyFaced": 1, "saves": 2, "punches": 1, "minutesPlayed": 90, "touches": 32, "rating": 7.4, "possessionLostCtrl": 8, "keeperSaveValue": 0.4154, "ratingVersions": {"original": 7.4, "alternative": 7.7}, "totalShots": 0, "passValueNormalized": 0.02, "dribbleValueNormalized": -0.02, "defensiveValueNormalized": 0.31, "goalkeeperValueNormalized": 0.37, "statisticsType": {"sportSlug": "football", "statisticsType": "player"}}}, {"player": {"name": "Dragan Bojat", "firstName": "Dragan Bojat", "lastName": "", "slug": "dragan-bojat", "shortName": "D. Bojat", "position": "D", "jerseyNumber": "23", "height": 177, "userCount": 248, "gender": "M", "country": {"alpha2": "RS", "alpha3": "SRB", "name": "Serbia", "slug": "serbia"}, "id": 1152937, "marketValueCurrency": "EUR", "dateOfBirthTimestamp": 1060473600, "proposedMarketValueRaw": {"value": 715000, "currency": "EUR"}, "fieldTranslations": {"nameTranslation": {"ar": "دراغان بوجات"}, "shortNameTranslation": {"ar": "د. بوجات"}}}, "teamId": 5149, "shirtNumber": 2, "jerseyNumber": "2", "position": "D", "substitute": false, "statistics": {"totalPass": 46, "accuratePass": 37, "totalLongBalls": 9, "accurateLongBalls": 5, "goalAssist": 0, "accurateOwnHalfPasses": 21, "totalOwnHalfPasses": 23, "accurateOppositionHalfPasses": 16, "totalOppositionHalfPasses": 23, "totalCross": 2, "accurateCross": 1, "duelLost": 3, "duelWon": 4, "dispossessed": 1, "totalContest": 3, "wonContest": 3, "onTargetScoringAttempt": 1, "totalClearance": 5, "ballRecovery": 4, "unsuccessfulTouch": 1, "wasFouled": 1, "fouls": 2, "minutesPlayed": 90, "touches": 73, "rating": 7.5, "possessionLostCtrl": 13, "keyPass": 3, "ratingVersions": {"original": 7.5, "alternative": 7.5}, "totalShots": 1, "shotValueNormalized": 0.21, "passValueNormalized": 0.33, "dribbleValueNormalized": 0.12, "defensiveValueNormalized": 0.23, "statisticsType": {"sportSlug": "football", "statisticsType": "player"}}}, {"player": {"name": "Ahmed Hadzimujovic", "firstName": "Ahmed Hadzimujovic", "slug": "ahmed-hadzimujovic", "shortName": "A. Hadzimujovic", "position": "D", "jerseyNumber": "4", "height": 190, "userCount": 132, "gender": "M", "country": {"alpha2": "RS", "alpha3": "SRB", "name": "Serbia", "slug": "serbia"}, "id": 1981962, "marketValueCurrency": "EUR", "dateOfBirthTimestamp": 1187308800, "proposedMarketValueRaw": {"value": 1000000, "currency": "EUR"}, "fieldTranslations": {"nameTranslation": {"ar": "أحمد هادزيموجوفيتش"}, "shortNameTranslation": {"ar": "أ. هادزيموجوفيتش"}}}, "teamId": 25736, "shirtNumber": 4, "jerseyNumber": "4", "position": "D", "substitute": false, "statistics": {"totalPass": 47, "accuratePass": 42, "totalLongBalls": 8, "accurateLongBalls": 5, "goalAssist": 0, "accurateOwnHalfPasses": 29, "totalOwnHalfPasses": 29, "accurateOppositionHalfPasses": 13, "totalOppositionHalfPasses": 18, "aerialLost": 2, "aerialWon": 4, "duelLost": 4, "duelWon": 6, "totalClearance": 5, "clearanceOffLine": 1, "outfielderBlock": 2, "ballRecovery": 3, "totalTackle": 2, "wonTackle": 2, "fouls": 2, "minutesPlayed": 90, "touches": 60, "rating": 7.9, "possessionLostCtrl": 6, "ratingVersions": {"original": 7.9, "alternative": 7.7}, "totalShots": 0, "passValueNormalized": 0.31, "dribbleValueNormalized": 0.09, "defensiveValueNormalized": 0.51, "statisticsType": {"sportSlug": "football", "statisticsType": "player"}}}, {"player": {"name": "Jovan Marinković", "slug": "jovan-marinkovic", "shortName": "J. Marinković", "position": "D", "jerseyNumber": "23", "height": 186, "userCount": 46, "gender": "M", "country": {"alpha2": "RS", "alpha3": "SRB", "name": "Serbia", "slug": "serbia"}, "id": 948696, "marketValueCurrency": "EUR", "dateOfBirthTimestamp": 842486400, "proposedMarketValueRaw": {"value": 480000, "currency": "EUR"}, "fieldTranslations": {"nameTranslation": {"ar": "يوفان مارينكوفيتش"}, "shortNameTranslation": {"ar": "ي. مارينكوفيتش"}}}, "teamId": 25736, "shirtNumber": 23, "jerseyNumber": "23", "position": "D", "substitute": false, "statistics": {"totalPass": 63, "accuratePass": 52, "totalLongBalls": 11, "accurateLongBalls": 4, "goalAssist": 0, "accurateOwnHalfPasses": 39, "totalOwnHalfPasses": 40, "accurateOppositionHalfPasses": 13, "totalOppositionHalfPasses": 23, "aerialLost": 5, "aerialWon": 2, "duelLost": 9, "duelWon": 4, "totalContest": 1, "totalClearance": 11, "outfielderBlock": 1, "ballRecovery": 7, "totalTackle": 1, "wonTackle": 1, "penaltyConceded": 1, "wasFouled": 1, "fouls": 3, "minutesPlayed": 90, "touches": 83, "rating": 6.8, "possessionLostCtrl": 12, "ratingVersions": {"original": 6.8, "alternative": 7.1}, "totalShots": 0, "passValueNormalized": 0.12, "dribbleValueNormalized": 0.05, "defensiveValueNormalized": -0.11, "statisticsType": {"sportSlug": "football", "statisticsType": "player"}}}, {"player": {"name": "Veljko Mirosavic", "slug": "veljko-mirosavic", "shortName": "V. Mirosavić", "position": "M", "jerseyNumber": "20", "height": 171, "userCount": 49, "gender": "M", "country": {"alpha2": "RS", "alpha3": "SRB", "name": "Serbia", "slug": "serbia"}, "id": 1153954, "marketValueCurrency": "EUR", "dateOfBirthTimestamp": 1118793600, "proposedMarketValueRaw": {"value": 205000, "currency": "EUR"}, "fieldTranslations": {"nameTranslation": {"ar": "يون ن / ساكيلاريديس م"}, "shortNameTranslation": {"ar": "ي. م"}}}, "teamId": 25736, "shirtNumber": 20, "jerseyNumber": "20", "position": "D", "substitute": false, "statistics": {"totalPass": 59, "accuratePass": 50, "totalLongBalls": 9, "accurateLongBalls": 3, "goalAssist": 1, "accurateOwnHalfPasses": 23, "totalOwnHalfPasses": 25, "accurateOppositionHalfPasses": 27, "totalOppositionHalfPasses": 34, "totalCross": 13, "accurateCross": 7, "aerialLost": 1, "aerialWon": 1, "duelLost": 2, "duelWon": 2, "bigChanceCreated": 1, "totalClearance": 3, "ballRecovery": 4, "totalTackle": 1, "unsuccessfulTouch": 1, "fouls": 1, "minutesPlayed": 90, "touches": 87, "rating": 7.6, "possessionLostCtrl": 21, "keyPass": 4, "ratingVersions": {"original": 7.6, "alternative": 7.9}, "totalShots": 0, "passValueNormalized": 0.76, "dribbleValueNormalized": 0.24, "defensiveValueNormalized": 0.15, "statisticsType": {"sportSlug": "football", "statisticsType": "player"}}}, {"player": {"name": "Skima Togbe", "firstName": "Skima Togbe", "slug": "skima-togbe", "shortName": "S. Togbe", "position": "M", "jerseyNumber": "16", "height": 173, "userCount": 94, "gender": "M", "country": {"alpha2": "GH", "alpha3": "GHA", "name": "Ghana", "slug": "ghana"}, "id": 1982067, "marketValueCurrency": "EUR", "dateOfBirthTimestamp": 1150329600, "proposedMarketValueRaw": {"value": 485000, "currency": "EUR"}, "fieldTranslations": {"nameTranslation": {"ar": "سكيما توغبي"}, "shortNameTranslation": {"ar": "س. توغبي"}}}, "teamId": 25736, "shirtNumber": 16, "jerseyNumber": "16", "position": "M", "substitute": false, "statistics": {"totalPass": 41, "accuratePass": 38, "totalLongBalls": 5, "accurateLongBalls": 4, "goalAssist": 0, "accurateOwnHalfPasses": 13, "totalOwnHalfPasses": 15, "accurateOppositionHalfPasses": 25, "totalOppositionHalfPasses": 26, "totalCross": 3, "accurateCross": 1, "duelLost": 1, "duelWon": 1, "totalContest": 2, "wonContest": 1, "shotOffTarget": 1, "onTargetScoringAttempt": 2, "interceptionWon": 1, "ballRecovery": 6, "unsuccessfulTouch": 1, "minutesPlayed": 71, "touches": 53, "rating": 7.8, "possessionLostCtrl": 7, "keyPass": 1, "ratingVersions": {"original": 7.8, "alternative": 7.3}, "totalShots": 3, "shotValueNormalized": 0.27, "passValueNormalized": 0.46, "dribbleValueNormalized": 0.44, "defensiveValueNormalized": 0.17, "statisticsType": {"sportSlug": "football", "statisticsType": "player"}}}, {"player": {"name": "Abdoulaye Cisse", "firstName": "", "lastName": "", "slug": "abdoulaye-cisse", "shortName": "A. Cisse", "position": "M", "jerseyNumber": "6", "height": 181, "userCount": 107, "gender": "M", "country": {"alpha2": "GN", "alpha3": "GIN", "name": "Guinea", "slug": "guinea"}, "id": 940100, "marketValueCurrency": "EUR", "dateOfBirthTimestamp": 824169600, "proposedMarketValueRaw": {"value": 720000, "currency": "EUR"}, "fieldTranslations": {"nameTranslation": {"ar": "عبد الله سي"}, "shortNameTranslation": {"ar": "ع. سي"}}}, "teamId": 5362, "shirtNumber": 6, "jerseyNumber": "6", "position": "M", "substitute": false, "captain": true, "statistics": {"totalPass": 53, "accuratePass": 46, "totalLongBalls": 6, "accurateLongBalls": 4, "goalAssist": 0, "accurateOwnHalfPasses": 27, "totalOwnHalfPasses": 28, "accurateOppositionHalfPasses": 19, "totalOppositionHalfPasses": 25, "aerialLost": 2, "aerialWon": 2, "duelLost": 6, "duelWon": 5, "challengeLost": 1, "dispossessed": 1, "totalContest": 1, "shotOffTarget": 1, "onTargetScoringAttempt": 1, "hitWoodwork": 1, "interceptionWon": 5, "ballRecovery": 10, "totalTackle": 1, "wonTackle": 1, "unsuccessfulTouch": 2, "wasFouled": 2, "fouls": 1, "minutesPlayed": 90, "touches": 70, "rating": 7.2, "possessionLostCtrl": 11, "keyPass": 1, "ratingVersions": {"original": 7.2, "alternative": 7.6}, "totalShots": 2, "shotValueNormalized": 0.01, "passValueNormalized": 0.28, "dribbleValueNormalized": 0.2, "defensiveValueNormalized": -0.02, "statisticsType": {"sportSlug": "football", "statisticsType": "player"}}}, {"player": {"name": "Ejike Opara", "slug": "ejike-opara", "shortName": "E. Opara", "position": "F", "jerseyNumber": "11", "height": 180, "userCount": 157, "gender": "M", "country": {"alpha2": "NG", "alpha3": "NGA", "name": "Nigeria", "slug": "nigeria"}, "id": 1617764, "marketValueCurrency": "EUR", "dateOfBirthTimestamp": 1120521600, "proposedMarketValueRaw": {"value": 970000, "currency": "EUR"}, "fieldTranslations": {"nameTranslation": {"ar": "إيجيكي أوبارا"}, "shortNameTranslation": {"ar": "إ. أوبارا"}}}, "teamId": 3009, "shirtNumber": 11, "jerseyNumber": "11", "position": "M", "substitute": false, "statistics": {"totalPass": 21, "accuratePass": 15, "totalLongBalls": 2, "accurateLongBalls": 2, "goalAssist": 0, "accurateOwnHalfPasses": 8, "totalOwnHalfPasses": 9, "accurateOppositionHalfPasses": 7, "totalOppositionHalfPasses": 12, "totalCross": 2, "accurateCross": 1, "aerialWon": 1, "duelLost": 3, "duelWon": 2, "challengeLost": 2, "blockedScoringAttempt": 2, "totalTackle": 1, "wonTackle": 1, "fouls": 1, "minutesPlayed": 64, "touches": 28, "rating": 6.8, "possessionLostCtrl": 7, "keyPass": 2, "ratingVersions": {"original": 6.8, "alternative": 7}, "totalShots": 2, "shotValueNormalized": -0.52, "passValueNormalized": 0.1, "dribbleValueNormalized": -0.01, "defensiveValueNormalized": -0.09, "statisticsType": {"sportSlug": "football", "statisticsType": "player"}}}, {"player": {"name": "Ivan Davidović", "firstName": "Ivan Davidovic", "slug": "ivan-davidovic", "shortName": "I. Davidović", "position": "M", "jerseyNumber": "24", "height": 180, "userCount": 55, "gender": "M", "country": {"alpha2": "RS", "alpha3": "SRB", "name": "Serbia", "slug": "serbia"}, "id": 1147753, "marketValueCurrency": "EUR", "dateOfBirthTimestamp": 822355200, "proposedMarketValueRaw": {"value": 385000, "currency": "EUR"}, "fieldTranslations": {"nameTranslation": {"ar": "إيفان دافيدوفيتش"}, "shortNameTranslation": {"ar": "إ. دافيدوفيتش"}}}, "teamId": 25736, "shirtNumber": 24, "jerseyNumber": "24", "position": "M", "substitute": false, "statistics": {"totalPass": 28, "accuratePass": 22, "totalLongBalls": 1, "goalAssist": 0, "accurateOwnHalfPasses": 10, "totalOwnHalfPasses": 10, "accurateOppositionHalfPasses": 12, "totalOppositionHalfPasses": 18, "totalCross": 3, "accurateCross": 1, "aerialLost": 4, "aerialWon": 3, "duelLost": 6, "duelWon": 5, "dispossessed": 1, "bigChanceCreated": 1, "shotOffTarget": 2, "onTargetScoringAttempt": 1, "totalClearance": 2, "interceptionWon": 1, "ballRecovery": 5, "unsuccessfulTouch": 3, "wasFouled": 2, "fouls": 1, "minutesPlayed": 90, "touches": 46, "rating": 6.3, "possessionLostCtrl": 12, "keyPass": 1, "ratingVersions": {"original": 6.3, "alternative": 7.6}, "totalShots": 3, "shotValueNormalized": -0.52, "passValueNormalized": -0.35, "dribbleValueNormalized": -0.64, "defensiveValueNormalized": 0.15, "statisticsType": {"sportSlug": "football", "statisticsType": "player"}}}, {"player": {"name": "Matija Malekinušić", "firstName": "", "lastName": "", "slug": "matija-malekinusic", "shortName": "M. Malekinušić", "position": "M", "jerseyNumber": "17", "height": 180, "userCount": 112, "gender": "M", "country": {"alpha2": "HR", "alpha3": "HRV", "name": "Croatia", "slug": "croatia"}, "id": 1003429, "marketValueCurrency": "EUR", "dateOfBirthTimestamp": 917395200, "proposedMarketValueRaw": {"value": 530000, "currency": "EUR"}, "fieldTranslations": {"nameTranslation": {"ar": "ماتيا مالاكينوشيتش", "bn": "মাতিজা মালেকিনুসিচ", "hi": "मतिजा मालेकिनुसिक"}, "shortNameTranslation": {"ar": "م. مالاكينوشيتش", "bn": "এম. মালেকিনুশিচ", "hi": "एम. मालेकिनुसिक"}}}, "teamId": 25736, "shirtNumber": 17, "jerseyNumber": "17", "position": "M", "substitute": false, "statistics": {"totalPass": 28, "accuratePass": 18, "totalLongBalls": 1, "accurateLongBalls": 1, "goalAssist": 0, "accurateOwnHalfPasses": 5, "totalOwnHalfPasses": 5, "accurateOppositionHalfPasses": 13, "totalOppositionHalfPasses": 23, "totalCross": 2, "accurateCross": 2, "aerialLost": 2, "aerialWon": 2, "duelLost": 5, "duelWon": 4, "challengeLost": 2, "totalContest": 1, "wonContest": 1, "shotOffTarget": 1, "onTargetScoringAttempt": 1, "ballRecovery": 4, "unsuccessfulTouch": 3, "wasFouled": 1, "fouls": 1, "minutesPlayed": 84, "touches": 39, "rating": 6.9, "possessionLostCtrl": 13, "keyPass": 3, "ratingVersions": {"original": 6.9, "alternative": 7.3}, "totalShots": 2, "shotValueNormalized": 0.26, "passValueNormalized": 0.16, "dribbleValueNormalized": 0.29, "defensiveValueNormalized": -0.08, "statisticsType": {"sportSlug": "football", "statisticsType": "player"}}}, {"player": {"name": "Stefan Stanisavljević", "slug": "stefan-stanisavljevic", "shortName": "S. Stanisavljević", "position": "F", "jerseyNumber": "18", "height": 188, "userCount": 77, "gender": "M", "country": {"alpha2": "RS", "alpha3": "SRB", "name": "Serbia", "slug": "serbia"}, "id": 1032770, "marketValueCurrency": "EUR", "dateOfBirthTimestamp": 1011139200, "proposedMarketValueRaw": {"value": 650000, "currency": "EUR"}, "fieldTranslations": {"nameTranslation": {"ar": "ستيفان ستانيسافليفيتش"}, "shortNameTranslation": {"ar": "س. ستانيسافليفيتش"}}}, "teamId": 25736, "shirtNumber": 18, "jerseyNumber": "18", "position": "F", "substitute": false, "statistics": {"totalPass": 12, "accuratePass": 10, "goalAssist": 0, "accurateOwnHalfPasses": 2, "totalOwnHalfPasses": 2, "accurateOppositionHalfPasses": 8, "totalOppositionHalfPasses": 10, "aerialLost": 4, "aerialWon": 2, "duelLost": 6, "duelWon": 4, "bigChanceMissed": 2, "shotOffTarget": 1, "onTargetScoringAttempt": 2, "blockedScoringAttempt": 1, "goals": 1, "ballRecovery": 2, "unsuccessfulTouch": 6, "wasFouled": 2, "fouls": 2, "minutesPlayed": 90, "touches": 28, "rating": 7.4, "possessionLostCtrl": 8, "keyPass": 1, "ratingVersions": {"original": 7.4, "alternative": 6.8}, "totalShots": 4, "shotValueNormalized": 0.52, "passValueNormalized": -0.23, "dribbleValueNormalized": 0.78, "defensiveValueNormalized": -0.02, "statisticsType": {"sportSlug": "football", "statisticsType": "player"}}}, {"player": {"name": "Luka Bijelović", "firstName": "", "lastName": "", "slug": "luka-bijelovic", "shortName": "L. Bijelović", "position": "F", "jerseyNumber": "28", "height": 186, "userCount": 48, "gender": "M", "country": {"alpha2": "RS", "alpha3": "SRB", "name": "Serbia", "slug": "serbia"}, "id": 944503, "marketValueCurrency": "EUR", "dateOfBirthTimestamp": 986947200, "proposedMarketValueRaw": {"value": 245000, "currency": "EUR"}, "fieldTranslations": {"nameTranslation": {"ar": "لوكا بييلوفيتش", "bn": "লুকা বিজেলোভিচ", "hi": "लुका बिजेलोविक"}, "shortNameTranslation": {"ar": "ل. بييلوفيتش", "bn": "এল. বিজেলোভিচ", "hi": "एल. बिजेलोविक"}}}, "teamId": 25736, "shirtNumber": 28, "jerseyNumber": "28", "position": "F", "substitute": true, "statistics": {"totalPass": 13, "accuratePass": 10, "goalAssist": 0, "accurateOwnHalfPasses": 3, "totalOwnHalfPasses": 3, "accurateOppositionHalfPasses": 7, "totalOppositionHalfPasses": 10, "aerialLost": 1, "duelLost": 3, "dispossessed": 2, "onTargetScoringAttempt": 2, "ballRecovery": 3, "unsuccessfulTouch": 1, "minutesPlayed": 26, "touches": 19, "rating": 6.3, "possessionLostCtrl": 6, "ratingVersions": {"original": 6.3, "alternative": 6.8}, "totalShots": 2, "shotValueNormalized": -0.25, "passValueNormalized": 0.09, "dribbleValueNormalized": 0.15, "defensiveValueNormalized": 0.13, "statisticsType": {"sportSlug": "football", "statisticsType": "player"}}}, {"player": {"name": "Semir Alić", "firstName": "", "lastName": "", "slug": "semir-alic", "shortName": "S. Alić", "position": "M", "jerseyNumber": "14", "height": 180, "userCount": 55, "gender": "M", "country": {"alpha2": "RS", "alpha3": "SRB", "name": "Serbia", "slug": "serbia"}, "id": 1102770, "marketValueCurrency": "EUR", "dateOfBirthTimestamp": 1080345600, "proposedMarketValueRaw": {"value": 625000, "currency": "EUR"}, "fieldTranslations": {"nameTranslation": {"ar": "سيمير عليتش"}, "shortNameTranslation": {"ar": "س. عليتش"}}}, "teamId": 25736, "shirtNumber": 14, "jerseyNumber": "14", "position": "M", "substitute": true, "statistics": {"totalPass": 5, "accuratePass": 3, "goalAssist": 0, "totalOwnHalfPasses": 1, "accurateOppositionHalfPasses": 3, "totalOppositionHalfPasses": 4, "aerialLost": 2, "duelLost": 2, "shotOffTarget": 1, "minutesPlayed": 19, "touches": 6, "rating": 6.4, "possessionLostCtrl": 2, "keyPass": 1, "ratingVersions": {"original": 6.4, "alternative": 6.6}, "totalShots": 1, "shotValueNormalized": -0.17, "passValueNormalized": -0.01, "dribbleValueNormalized": -0.22, "defensiveValueNormalized": -0.01, "statisticsType": {"sportSlug": "football", "statisticsType": "player"}}}, {"player": {"name": "Mihajlo Petković", "firstName": "Mihajlo", "lastName": "Petkovic", "slug": "mihajlo-petkovic", "shortName": "M. Petković", "position": "M", "jerseyNumber": "21", "height": 182, "userCount": 153, "gender": "M", "country": {"alpha2": "RS", "alpha3": "SRB", "name": "Serbia", "slug": "serbia"}, "id": 1100966, "marketValueCurrency": "EUR", "dateOfBirthTimestamp": 1085616000, "proposedMarketValueRaw": {"value": 1600000, "currency": "EUR"}, "fieldTranslations": {"nameTranslation": {"ar": "ميهايلو بيتكوفيتش", "bn": "মিহাজলো পেটকোভিচ", "hi": "मिहाज्लो पेतकोविच"}, "shortNameTranslation": {"ar": "م. بيتكوفيتش", "bn": "এম. পেটকোভিচ", "hi": "एम. पेतकोविच"}}}, "teamId": 25736, "shirtNumber": 21, "jerseyNumber": "21", "position": "M", "substitute": true, "statistics": {"totalPass": 1, "goalAssist": 0, "totalOwnHalfPasses": 1, "minutesPlayed": 13, "touches": 2, "rating": 6.6, "possessionLostCtrl": 1, "ratingVersions": {"original": 6.6, "alternative": 6.5}, "totalShots": 0, "passValueNormalized": -0.02, "dribbleValueNormalized": 0.04, "defensiveValueNormalized": 0.13, "statisticsType": {"sportSlug": "football", "statisticsType": "player"}}}, {"player": {"name": "Filip Bačkulja", "slug": "backulja-filip", "shortName": "F. Bačkulja", "position": "D", "jerseyNumber": "15", "height": 187, "userCount": 55, "gender": "M", "country": {"alpha2": "RS", "alpha3": "SRB", "name": "Serbia", "slug": "serbia"}, "id": 999049, "marketValueCurrency": "EUR", "dateOfBirthTimestamp": 1024963200, "proposedMarketValueRaw": {"value": 325000, "currency": "EUR"}, "fieldTranslations": {"nameTranslation": {"ar": "فيليب باتشكويا"}, "shortNameTranslation": {"ar": "ف. باتشكويا"}}}, "teamId": 25736, "shirtNumber": 15, "jerseyNumber": "15", "position": "D", "substitute": true, "statistics": {"totalShots": 0, "statisticsType": {"sportSlug": "football", "statisticsType": "player"}}}, {"player": {"name": "Dominic Sadi", "firstName": "Dominic Sadi", "slug": "sadi-dominic", "shortName": "D. Sadi", "position": "F", "jerseyNumber": "30", "height": 174, "userCount": 184, "gender": "M", "country": {"alpha2": "EN", "alpha3": "ENG", "name": "England", "slug": "england"}, "id": 1398550, "marketValueCurrency": "EUR", "dateOfBirthTimestamp": 1062460800, "proposedMarketValueRaw": {"value": 135000, "currency": "EUR"}, "fieldTranslations": {"nameTranslation": {"ar": "سادي، دومينيك", "bn": "সাদি, ডমিনিক", "hi": "सादी, डोमिनिक"}, "shortNameTranslation": {"ar": "د. سادي", "bn": "ডি. সাদি", "hi": "डी. डोमिनिक"}}}, "teamId": 25736, "shirtNumber": 10, "jerseyNumber": "10", "position": "M", "substitute": true, "statistics": {"totalShots": 0, "statisticsType": {"sportSlug": "football", "statisticsType": "player"}}}, {"player": {"name": "Jovan Manev", "firstName": "Jovan Manev", "slug": "jovan-manev", "shortName": "J. Manev", "position": "D", "jerseyNumber": "29", "height": 185, "userCount": 182, "gender": "M", "country": {"alpha2": "MK", "alpha3": "MKD", "name": "North Macedonia", "slug": "north-macedonia"}, "id": 1111781, "marketValueCurrency": "EUR", "dateOfBirthTimestamp": 980380800, "proposedMarketValueRaw": {"value": 360000, "currency": "EUR"}, "fieldTranslations": {"nameTranslation": {"ar": "جوفان مانيف", "bn": "জোভান মানেভ", "hi": "जोवन मानेव"}, "shortNameTranslation": {"ar": "ج. مانيف", "bn": "জে. মানেভ", "hi": "जे. मानेव"}}}, "teamId": 25736, "shirtNumber": 29, "jerseyNumber": "29", "position": "D", "substitute": true, "statistics": {"totalShots": 0, "statisticsType": {"sportSlug": "football", "statisticsType": "player"}}}, {"player": {"name": "Saladin Mecinovic", "slug": "saladin-mecinovic", "shortName": "S. Mećinović", "position": "G", "jerseyNumber": "25", "height": 188, "userCount": 31, "gender": "M", "country": {"alpha2": "RS", "alpha3": "SRB", "name": "Serbia", "slug": "serbia"}, "id": 1617763, "marketValueCurrency": "EUR", "dateOfBirthTimestamp": 1134000000, "fieldTranslations": {"nameTranslation": {"ar": "صلاح الدين ميتشينوفيتش"}, "shortNameTranslation": {"ar": "ص. ميتشينوفيتش"}}}, "teamId": 25736, "shirtNumber": 25, "jerseyNumber": "25", "position": "G", "substitute": true, "statistics": {"totalShots": 0, "statisticsType": {"sportSlug": "football", "statisticsType": "player"}}}, {"player": {"name": "Abdulsamed Abdullahi", "slug": "abdulsamed-abdullahi", "shortName": "A. Abdullahi", "position": "M", "jerseyNumber": "8", "height": 183, "userCount": 106, "gender": "M", "country": {"alpha2": "SO", "alpha3": "SOM", "name": "Somalia", "slug": "somalia"}, "id": 907763, "marketValueCurrency": "EUR", "dateOfBirthTimestamp": 853632000, "proposedMarketValueRaw": {"value": 230000, "currency": "EUR"}, "fieldTranslations": {"nameTranslation": {"ar": "عبدالسلام عبد اللهي"}, "shortNameTranslation": {"ar": "ع. اللهي"}}}, "teamId": 25736, "shirtNumber": 8, "jerseyNumber": "8", "position": "M", "substitute": true, "statistics": {"totalShots": 0, "statisticsType": {"sportSlug": "football", "statisticsType": "player"}}}, {"player": {"name": "Zoran Alilović", "slug": "zoran-alilovic", "shortName": "Z. Alilović", "position": "M", "jerseyNumber": "31", "height": 175, "userCount": 229, "gender": "M", "country": {"alpha2": "RS", "alpha3": "SRB", "name": "Serbia", "slug": "serbia"}, "id": 1493919, "marketValueCurrency": "EUR", "dateOfBirthTimestamp": 1142294400, "proposedMarketValueRaw": {"value": 425000, "currency": "EUR"}, "fieldTranslations": {"nameTranslation": {"ar": "زوران أليلوفيتش"}, "shortNameTranslation": {"ar": "ز. أليلوفيتش"}}}, "teamId": 25736, "shirtNumber": 31, "jerseyNumber": "31", "position": "M", "substitute": true, "statistics": {"totalShots": 0, "statisticsType": {"sportSlug": "football", "statisticsType": "player"}}}, {"player": {"name": "Bob Murphy Omoregbe", "firstName": "Bob Murphy", "lastName": "Omoregbe", "slug": "omoregbe-bob-murphy", "shortName": "B. M. Omoregbe", "position": "M", "jerseyNumber": "7", "height": 185, "userCount": 193, "gender": "M", "country": {"alpha2": "IT", "alpha3": "ITA", "name": "Italy", "slug": "italy"}, "id": 1175945, "marketValueCurrency": "EUR", "dateOfBirthTimestamp": 1067990400, "proposedMarketValueRaw": {"value": 290000, "currency": "EUR"}, "fieldTranslations": {"nameTranslation": {"ar": "بوب ميرفي أومورغبي"}, "shortNameTranslation": {"ar": "ب. أومورغبي"}}}, "teamId": 25736, "shirtNumber": 7, "jerseyNumber": "7", "position": "F", "substitute": true, "statistics": {"totalShots": 0, "statisticsType": {"sportSlug": "football", "statisticsType": "player"}}}, {"player": {"name": "Ensar Brunčević", "slug": "ensar-bruncevic", "shortName": "E. Brunčević", "position": "D", "jerseyNumber": "5", "height": 196, "userCount": 36, "gender": "M", "country": {"alpha2": "RS", "alpha3": "SRB", "name": "Serbia", "slug": "serbia"}, "id": 1023999, "marketValueCurrency": "EUR", "dateOfBirthTimestamp": 918864000, "proposedMarketValueRaw": {"value": 190000, "currency": "EUR"}, "fieldTranslations": {"nameTranslation": {"ar": "إنصار برونتشيفيتش"}, "shortNameTranslation": {"ar": "إ. برونتشيفيتش"}}}, "teamId": 25736, "shirtNumber": 5, "jerseyNumber": "5", "position": "D", "substitute": true, "statistics": {"totalShots": 0, "statisticsType": {"sportSlug": "football", "statisticsType": "player"}}}], "supportStaff": [], "formation": "4-2-3-1", "playerColor": {"primary": "0011ff", "number": "ffffff", "outline": "0011ff", "fancyNumber": "ffffff"}, "goalkeeperColor": {"primary": "9e9e9e", "number": "202020", "outline": "9e9e9e", "fancyNumber": "222226"}}, "away": {"players": [{"player": {"name": "Saša Stamenković", "firstName": "", "lastName": "", "slug": "sasa-stamenkovic", "shortName": "S. Stamenković", "position": "G", "jerseyNumber": "1", "height": 194, "userCount": 63, "gender": "M", "country": {"alpha2": "RS", "alpha3": "SRB", "name": "Serbia", "slug": "serbia"}, "id": 38583, "marketValueCurrency": "EUR", "dateOfBirthTimestamp": 473731200, "proposedMarketValueRaw": {"value": 48000, "currency": "EUR"}, "fieldTranslations": {"nameTranslation": {"ar": "ساشا ستامنكوفيتش"}, "shortNameTranslation": {"ar": "س. ستامنكوفيتش"}}}, "teamId": 7771, "shirtNumber": 1, "jerseyNumber": "1", "position": "G", "substitute": false, "statistics": {"totalPass": 33, "accuratePass": 25, "totalLongBalls": 19, "accurateLongBalls": 11, "goalAssist": 0, "accurateOwnHalfPasses": 21, "totalOwnHalfPasses": 22, "accurateOppositionHalfPasses": 4, "totalOppositionHalfPasses": 11, "totalClearance": 1, "ballRecovery": 9, "goodHighClaim": 1, "savedShotsFromInsideTheBox": 7, "saves": 9, "minutesPlayed": 90, "touches": 50, "rating": 9.9, "possessionLostCtrl": 8, "keeperSaveValue": 1.8345, "ratingVersions": {"original": 9.9, "alternative": 8.6}, "totalShots": 0, "passValueNormalized": 0.12, "dribbleValueNormalized": -0.01, "defensiveValueNormalized": 0.24, "goalkeeperValueNormalized": 1, "statisticsType": {"sportSlug": "football", "statisticsType": "player"}}}, {"player": {"name": "Aleksandar Varjačić", "firstName": "", "lastName": "", "slug": "aleksandar-varjacic", "shortName": "A. Varjačić", "position": "D", "jerseyNumber": "17", "height": 187, "userCount": 12, "gender": "M", "country": {"alpha2": "RS", "alpha3": "SRB", "name": "Serbia", "slug": "serbia"}, "id": 795855, "marketValueCurrency": "EUR", "dateOfBirthTimestamp": 674956800, "proposedMarketValueRaw": {"value": 53000, "currency": "EUR"}, "fieldTranslations": {"nameTranslation": {"ar": "ألكسندر فارجاتجيتش"}, "shortNameTranslation": {"ar": "أ. فارجاتجيتش"}}}, "teamId": 7771, "shirtNumber": 17, "jerseyNumber": "17", "position": "D", "substitute": false, "statistics": {"totalPass": 13, "accuratePass": 7, "totalLongBalls": 5, "accurateLongBalls": 1, "goalAssist": 0, "accurateOwnHalfPasses": 5, "totalOwnHalfPasses": 6, "accurateOppositionHalfPasses": 2, "totalOppositionHalfPasses": 7, "totalCross": 1, "aerialLost": 1, "aerialWon": 1, "duelLost": 1, "duelWon": 2, "totalContest": 1, "wonContest": 1, "totalClearance": 3, "outfielderBlock": 1, "minutesPlayed": 45, "touches": 22, "rating": 6.4, "possessionLostCtrl": 9, "ratingVersions": {"original": 6.4, "alternative": 6.4}, "totalShots": 0, "passValueNormalized": 0.04, "dribbleValueNormalized": 0, "defensiveValueNormalized": 0.22, "statisticsType": {"sportSlug": "football", "statisticsType": "player"}}}, {"player": {"name": "Nikola Ćirković", "firstName": "", "lastName": "", "slug": "nikola-cirkovic", "shortName": "N. Ćirković", "position": "D", "jerseyNumber": "30", "height": 188, "userCount": 9, "gender": "M", "country": {"alpha2": "RS", "alpha3": "SRB", "name": "Serbia", "slug": "serbia"}, "id": 814416, "marketValueCurrency": "EUR", "dateOfBirthTimestamp": 691804800, "proposedMarketValueRaw": {"value": 130000, "currency": "EUR"}, "fieldTranslations": {"nameTranslation": {"ar": "نيكولا تشيركوفيتش", "bn": "নিকোলা সার্কোভিচ", "hi": "निकोला सिर्कोविक"}, "shortNameTranslation": {"ar": "ن. تشيركوفيتش", "bn": "এন. জিরকোভিচ", "hi": "एन. सिर्कोविक"}}}, "teamId": 7771, "shirtNumber": 30, "jerseyNumber": "30", "position": "D", "substitute": false, "statistics": {"totalPass": 60, "accuratePass": 48, "totalLongBalls": 15, "accurateLongBalls": 10, "goalAssist": 0, "accurateOwnHalfPasses": 22, "totalOwnHalfPasses": 24, "accurateOppositionHalfPasses": 26, "totalOppositionHalfPasses": 36, "aerialLost": 1, "aerialWon": 1, "duelLost": 1, "duelWon": 5, "totalContest": 1, "wonContest": 1, "bigChanceMissed": 1, "onTargetScoringAttempt": 1, "totalClearance": 3, "interceptionWon": 2, "ballRecovery": 7, "totalTackle": 2, "wonTackle": 1, "wasFouled": 1, "minutesPlayed": 90, "touches": 72, "rating": 7.2, "possessionLostCtrl": 12, "ratingVersions": {"original": 7.2, "alternative": 7.4}, "totalShots": 1, "shotValueNormalized": 0.02, "passValueNormalized": 0.33, "dribbleValueNormalized": 0.07, "defensiveValueNormalized": -0.17, "statisticsType": {"sportSlug": "football", "statisticsType": "player"}}}, {"player": {"name": "Dušan Cvetinović", "slug": "dusan-cvetinovic", "shortName": "D. Cvetinović", "position": "D", "jerseyNumber": "40", "height": 186, "userCount": 25, "gender": "M", "country": {"alpha2": "RS", "alpha3": "SRB", "name": "Serbia", "slug": "serbia"}, "id": 69023, "marketValueCurrency": "EUR", "dateOfBirthTimestamp": 598924800, "proposedMarketValueRaw": {"value": 47000, "currency": "EUR"}, "fieldTranslations": {"nameTranslation": {"ar": "دوشان سفيتينوفيتش", "bn": "দুসান সিভেটিনোভিচ", "hi": "दुसान क्वेटिनोविच"}, "shortNameTranslation": {"ar": "د. سفيتينوفيتش", "bn": "ডি. সিভেটিনোভিচ", "hi": "डी. क्वेटिनोविच"}}}, "teamId": 7771, "shirtNumber": 40, "jerseyNumber": "40", "position": "D", "substitute": false, "statistics": {"totalPass": 17, "accuratePass": 11, "totalLongBalls": 3, "goalAssist": 0, "accurateOwnHalfPasses": 9, "totalOwnHalfPasses": 14, "accurateOppositionHalfPasses": 2, "totalOppositionHalfPasses": 3, "aerialLost": 1, "aerialWon": 1, "duelLost": 2, "duelWon": 1, "totalClearance": 2, "outfielderBlock": 2, "interceptionWon": 1, "ballRecovery": 4, "fouls": 1, "minutesPlayed": 45, "touches": 23, "rating": 6.7, "possessionLostCtrl": 6, "ratingVersions": {"original": 6.7, "alternative": 6.6}, "totalShots": 0, "passValueNormalized": -0.01, "dribbleValueNormalized": -0.01, "defensiveValueNormalized": 0.44, "statisticsType": {"sportSlug": "football", "statisticsType": "player"}}}, {"player": {"name": "Mihailo Oreščanin", "firstName": "", "lastName": "", "slug": "mihailo-orescanin", "shortName": "M. Oreščanin", "position": "D", "jerseyNumber": "37", "height": 189, "userCount": 14, "gender": "M", "country": {"alpha2": "RS", "alpha3": "SRB", "name": "Serbia", "slug": "serbia"}, "id": 1022062, "marketValueCurrency": "EUR", "dateOfBirthTimestamp": 873590400, "proposedMarketValueRaw": {"value": 530000, "currency": "EUR"}, "fieldTranslations": {"nameTranslation": {"ar": "ميهايلو أوريسكانين"}, "shortNameTranslation": {"ar": "م. أوريسكانين"}}}, "teamId": 7771, "shirtNumber": 37, "jerseyNumber": "37", "position": "D", "substitute": false, "statistics": {"totalPass": 45, "accuratePass": 40, "totalLongBalls": 8, "accurateLongBalls": 5, "goalAssist": 0, "accurateOwnHalfPasses": 25, "totalOwnHalfPasses": 26, "accurateOppositionHalfPasses": 15, "totalOppositionHalfPasses": 19, "aerialLost": 2, "aerialWon": 4, "duelLost": 2, "duelWon": 6, "totalClearance": 15, "interceptionWon": 2, "ballRecovery": 3, "unsuccessfulTouch": 2, "wasFouled": 2, "minutesPlayed": 90, "touches": 67, "rating": 7, "possessionLostCtrl": 7, "ratingVersions": {"original": 7, "alternative": 7.2}, "totalShots": 0, "passValueNormalized": 0.1, "dribbleValueNormalized": 0.18, "defensiveValueNormalized": -0.03, "statisticsType": {"sportSlug": "football", "statisticsType": "player"}}}, {"player": {"name": "Žarko Udovičić", "slug": "zarko-udovicic", "shortName": "Ž. Udovičić", "position": "D", "jerseyNumber": "33", "height": 185, "userCount": 17, "gender": "M", "country": {"alpha2": "RS", "alpha3": "SRB", "name": "Serbia", "slug": "serbia"}, "id": 795938, "marketValueCurrency": "EUR", "dateOfBirthTimestamp": 557366400, "fieldTranslations": {"nameTranslation": {"ar": "زاركو أودوفيتشيتش", "bn": "জারকো উডোভিচ", "hi": "ज़ारको उदोविचिक"}, "shortNameTranslation": {"ar": "ز. أودوفيتشيتش", "bn": "জেড. উডোভিচ", "hi": "ज़ेड. उदोविचिक"}}}, "teamId": 7771, "shirtNumber": 33, "jerseyNumber": "33", "position": "D", "substitute": false, "captain": true, "statistics": {"totalPass": 27, "accuratePass": 19, "totalLongBalls": 7, "accurateLongBalls": 5, "goalAssist": 0, "accurateOwnHalfPasses": 9, "totalOwnHalfPasses": 9, "accurateOppositionHalfPasses": 10, "totalOppositionHalfPasses": 18, "totalCross": 2, "duelLost": 1, "duelWon": 3, "challengeLost": 1, "totalContest": 2, "wonContest": 2, "shotOffTarget": 1, "blockedScoringAttempt": 1, "totalClearance": 3, "interceptionWon": 1, "ballRecovery": 1, "totalTackle": 1, "wonTackle": 1, "minutesPlayed": 90, "touches": 50, "rating": 6.7, "possessionLostCtrl": 13, "ratingVersions": {"original": 6.7, "alternative": 6.9}, "totalShots": 2, "shotValueNormalized": -0.2, "passValueNormalized": 0.04, "dribbleValueNormalized": 0.3, "defensiveValueNormalized": -0.14, "statisticsType": {"sportSlug": "football", "statisticsType": "player"}}}, {"player": {"name": "Nemanja Milojević", "firstName": "", "lastName": "", "slug": "nemanja-milojevic", "shortName": "N. Milojević", "position": "M", "jerseyNumber": "38", "height": 183, "userCount": 65, "gender": "M", "country": {"alpha2": "GR", "alpha3": "GRC", "name": "Greece", "slug": "greece"}, "id": 837894, "marketValueCurrency": "EUR", "dateOfBirthTimestamp": 888192000, "proposedMarketValueRaw": {"value": 580000, "currency": "EUR"}, "fieldTranslations": {"nameTranslation": {"ar": "نيمانجا ميلوجيفيتش"}, "shortNameTranslation": {"ar": "ن. ميلوجيفيتش"}}}, "teamId": 7771, "shirtNumber": 38, "jerseyNumber": "38", "position": "M", "substitute": false, "statistics": {"totalPass": 11, "accuratePass": 10, "totalLongBalls": 1, "accurateLongBalls": 1, "goalAssist": 0, "accurateOwnHalfPasses": 6, "totalOwnHalfPasses": 6, "accurateOppositionHalfPasses": 4, "totalOppositionHalfPasses": 5, "duelLost": 1, "duelWon": 1, "challengeLost": 1, "blockedScoringAttempt": 1, "totalClearance": 1, "ballRecovery": 1, "totalTackle": 1, "wonTackle": 1, "minutesPlayed": 45, "touches": 15, "rating": 6.6, "possessionLostCtrl": 1, "keyPass": 1, "ratingVersions": {"original": 6.6, "alternative": 6.7}, "totalShots": 1, "shotValueNormalized": -0.12, "passValueNormalized": -0.04, "dribbleValueNormalized": 0.16, "defensiveValueNormalized": -0.05, "statisticsType": {"sportSlug": "football", "statisticsType": "player"}}}, {"player": {"name": "Janko Tumbasević", "firstName": "", "lastName": "", "slug": "janko-tumbasevic", "shortName": "J. Tumbasević", "position": "M", "jerseyNumber": "8", "height": 179, "userCount": 13, "gender": "M", "country": {"alpha2": "ME", "alpha3": "MNE", "name": "Montenegro", "slug": "montenegro"}, "id": 27863, "marketValueCurrency": "EUR", "dateOfBirthTimestamp": 474508800, "proposedMarketValueRaw": {"value": 52000, "currency": "EUR"}, "fieldTranslations": {"nameTranslation": {"ar": "جانكو تومباسيفيتش", "bn": "জানকো টাম্বাসেভিচ", "hi": "जान्को टुम्बासेविक"}, "shortNameTranslation": {"ar": "ج. تومباسيفيتش", "bn": "জে. টাম্বাসেভিচ", "hi": "जे. टुम्बासेविक"}}}, "teamId": 7771, "shirtNumber": 8, "jerseyNumber": "8", "position": "M", "substitute": false, "statistics": {"totalPass": 45, "accuratePass": 36, "totalLongBalls": 4, "accurateLongBalls": 2, "goalAssist": 0, "accurateOwnHalfPasses": 24, "totalOwnHalfPasses": 26, "accurateOppositionHalfPasses": 12, "totalOppositionHalfPasses": 19, "aerialWon": 3, "duelLost": 2, "duelWon": 6, "totalContest": 1, "wonContest": 1, "totalClearance": 1, "ballRecovery": 8, "totalTackle": 2, "wonTackle": 1, "unsuccessfulTouch": 2, "fouls": 2, "minutesPlayed": 90, "touches": 55, "rating": 6.6, "possessionLostCtrl": 11, "ratingVersions": {"original": 6.6, "alternative": 6.7}, "totalShots": 0, "passValueNormalized": -0.03, "dribbleValueNormalized": 0.11, "defensiveValueNormalized": -0.06, "statisticsType": {"sportSlug": "football", "statisticsType": "player"}}}, {"player": {"name": "Uroš Ljubomirac", "firstName": "", "lastName": "", "slug": "uros-ljubomirac", "shortName": "U. Ljubomirac", "position": "M", "jerseyNumber": "77", "height": 181, "userCount": 7, "gender": "M", "country": {"alpha2": "RS", "alpha3": "SRB", "name": "Serbia", "slug": "serbia"}, "id": 892174, "marketValueCurrency": "EUR", "dateOfBirthTimestamp": 639878400, "proposedMarketValueRaw": {"value": 52000, "currency": "EUR"}, "fieldTranslations": {"nameTranslation": {"ar": "أوروس ليوبوميراك", "bn": "উরোস লুবোমিরাক", "hi": "उरोस लुबोमिराक"}, "shortNameTranslation": {"ar": "أ. ليوبوميراك", "bn": "ইউ. জুবোমিরাক", "hi": "यू. लुजोमिराक"}}}, "teamId": 7771, "shirtNumber": 77, "jerseyNumber": "77", "position": "M", "substitute": false, "statistics": {"totalPass": 28, "accuratePass": 20, "totalLongBalls": 2, "accurateLongBalls": 1, "goalAssist": 0, "accurateOwnHalfPasses": 8, "totalOwnHalfPasses": 9, "accurateOppositionHalfPasses": 12, "totalOppositionHalfPasses": 19, "aerialLost": 1, "aerialWon": 2, "duelLost": 5, "duelWon": 4, "challengeLost": 1, "dispossessed": 1, "totalContest": 1, "ballRecovery": 2, "unsuccessfulTouch": 1, "wasFouled": 2, "fouls": 1, "minutesPlayed": 82, "touches": 35, "rating": 6.5, "possessionLostCtrl": 11, "ratingVersions": {"original": 6.5, "alternative": 6.3}, "totalShots": 0, "passValueNormalized": 0.05, "dribbleValueNormalized": 0.11, "defensiveValueNormalized": -0.1, "statisticsType": {"sportSlug": "football", "statisticsType": "player"}}}, {"player": {"name": "Uroš Sremčević", "slug": "uros-sremcevic", "shortName": "U. Sremčević", "position": "F", "jerseyNumber": "17", "height": 185, "userCount": 1585, "gender": "M", "country": {"alpha2": "RS", "alpha3": "SRB", "name": "Serbia", "slug": "serbia"}, "id": 1166063, "marketValueCurrency": "EUR", "dateOfBirthTimestamp": 1145836800, "proposedMarketValueRaw": {"value": 905000, "currency": "EUR"}, "fieldTranslations": {"nameTranslation": {"ar": "أوروش سريمشيفيتش"}, "shortNameTranslation": {"ar": "أ. سريمشيفيتش"}}}, "teamId": 7674, "shirtNumber": 19, "jerseyNumber": "19", "position": "F", "substitute": false, "statistics": {"totalPass": 13, "accuratePass": 7, "goalAssist": 0, "accurateOwnHalfPasses": 1, "totalOwnHalfPasses": 3, "accurateOppositionHalfPasses": 6, "totalOppositionHalfPasses": 10, "aerialLost": 6, "aerialWon": 3, "duelLost": 8, "duelWon": 4, "challengeLost": 1, "bigChanceMissed": 1, "shotOffTarget": 1, "totalClearance": 2, "unsuccessfulTouch": 2, "wasFouled": 1, "fouls": 1, "minutesPlayed": 45, "touches": 21, "rating": 6.5, "possessionLostCtrl": 8, "keyPass": 1, "ratingVersions": {"original": 6.5, "alternative": 6.7}, "totalShots": 1, "shotValueNormalized": -0.4, "passValueNormalized": -0.26, "dribbleValueNormalized": 0.27, "defensiveValueNormalized": 0.13, "statisticsType": {"sportSlug": "football", "statisticsType": "player"}}}, {"player": {"name": "Jovan Ćirić", "slug": "jovan-ciric", "shortName": "J. Ćirić", "position": "M", "jerseyNumber": "25", "height": 179, "userCount": 73, "gender": "M", "country": {"alpha2": "RS", "alpha3": "SRB", "name": "Serbia", "slug": "serbia"}, "id": 1595643, "marketValueCurrency": "EUR", "dateOfBirthTimestamp": 1172361600, "proposedMarketValueRaw": {"value": 755000, "currency": "EUR"}, "fieldTranslations": {"nameTranslation": {"ar": "يوفان تشيريتش"}, "shortNameTranslation": {"ar": "ي. تشيريتش"}}}, "teamId": 7771, "shirtNumber": 25, "jerseyNumber": "25", "position": "F", "substitute": false, "statistics": {"totalPass": 12, "accuratePass": 9, "totalLongBalls": 1, "goalAssist": 0, "accurateOwnHalfPasses": 3, "totalOwnHalfPasses": 3, "accurateOppositionHalfPasses": 6, "totalOppositionHalfPasses": 9, "totalCross": 5, "accurateCross": 1, "aerialLost": 1, "duelLost": 6, "duelWon": 3, "challengeLost": 1, "dispossessed": 1, "totalContest": 2, "bigChanceCreated": 1, "onTargetScoringAttempt": 1, "ballRecovery": 2, "unsuccessfulTouch": 5, "wasFouled": 3, "fouls": 1, "minutesPlayed": 90, "touches": 35, "rating": 6.4, "possessionLostCtrl": 16, "keyPass": 1, "ratingVersions": {"original": 6.4, "alternative": 6.6}, "totalShots": 1, "shotValueNormalized": -0.33, "passValueNormalized": 0.01, "dribbleValueNormalized": 0.31, "defensiveValueNormalized": -0.06, "statisticsType": {"sportSlug": "football", "statisticsType": "player"}}}, {"player": {"name": "Irfan Hadžić", "slug": "irfan-hadzic", "shortName": "I. Hadžić", "position": "F", "jerseyNumber": "9", "height": 191, "userCount": 36, "gender": "M", "country": {"alpha2": "BA", "alpha3": "BIH", "name": "Bosnia & Herzegovina", "slug": "bosnia-and-herzegovina"}, "id": 173957, "marketValueCurrency": "EUR", "dateOfBirthTimestamp": 739238400, "proposedMarketValueRaw": {"value": 165000, "currency": "EUR"}, "fieldTranslations": {"nameTranslation": {"ar": "عرفان حادزيتش", "bn": "ইরফান হাদজিচ", "hi": "इरफ़ान हडज़िक"}, "shortNameTranslation": {"ar": "ع. حادزيتش", "bn": "আই. হাদজিচ", "hi": "आई. हडज़िक"}}}, "teamId": 7771, "shirtNumber": 9, "jerseyNumber": "9", "position": "F", "substitute": true, "statistics": {"totalPass": 18, "accuratePass": 11, "goalAssist": 0, "accurateOwnHalfPasses": 6, "totalOwnHalfPasses": 7, "accurateOppositionHalfPasses": 5, "totalOppositionHalfPasses": 11, "aerialLost": 2, "aerialWon": 6, "duelLost": 3, "duelWon": 8, "totalContest": 1, "shotOffTarget": 1, "unsuccessfulTouch": 4, "wasFouled": 2, "minutesPlayed": 45, "touches": 28, "rating": 6.7, "possessionLostCtrl": 12, "keyPass": 1, "ratingVersions": {"original": 6.7, "alternative": 6.9}, "totalShots": 1, "shotValueNormalized": -0.29, "passValueNormalized": -0.27, "dribbleValueNormalized": 0.12, "defensiveValueNormalized": -0.04, "statisticsType": {"sportSlug": "football", "statisticsType": "player"}}}, {"player": {"name": "Petar Bojić", "firstName": "", "lastName": "", "slug": "petar-bojic", "shortName": "P. Bojić", "position": "M", "jerseyNumber": "10", "height": 186, "userCount": 26, "gender": "M", "country": {"alpha2": "RS", "alpha3": "SRB", "name": "Serbia", "slug": "serbia"}, "id": 126558, "marketValueCurrency": "EUR", "dateOfBirthTimestamp": 683942400, "proposedMarketValueRaw": {"value": 120000, "currency": "EUR"}, "fieldTranslations": {"nameTranslation": {"ar": "بيتر بويتش", "bn": "পেটার বোজিচ", "hi": "पीटर बोजिक"}, "shortNameTranslation": {"ar": "ب. بويتش", "bn": "পি. বোজিচ", "hi": "पी. बोजिक"}}}, "teamId": 7771, "shirtNumber": 10, "jerseyNumber": "10", "position": "M", "substitute": true, "statistics": {"totalPass": 12, "accuratePass": 8, "totalLongBalls": 1, "goalAssist": 0, "accurateOwnHalfPasses": 2, "totalOwnHalfPasses": 3, "accurateOppositionHalfPasses": 6, "totalOppositionHalfPasses": 9, "duelLost": 1, "duelWon": 2, "interceptionWon": 2, "ballRecovery": 2, "unsuccessfulTouch": 1, "wasFouled": 2, "fouls": 2, "penaltyWon": 1, "minutesPlayed": 45, "touches": 18, "rating": 7.3, "possessionLostCtrl": 5, "ratingVersions": {"original": 7.3, "alternative": 7}, "totalShots": 0, "passValueNormalized": -0.08, "dribbleValueNormalized": 0.36, "defensiveValueNormalized": 0, "statisticsType": {"sportSlug": "football", "statisticsType": "player"}}}, {"player": {"name": "Đorđe Marinković", "firstName": "Djordje Marinkovic", "slug": "djordje-marinkovic", "shortName": "Đ. Marinković", "position": "M", "jerseyNumber": "15", "height": 180, "userCount": 9, "gender": "M", "country": {"alpha2": "RS", "alpha3": "SRB", "name": "Serbia", "slug": "serbia"}, "id": 1595520, "marketValueCurrency": "EUR", "dateOfBirthTimestamp": 1137283200, "proposedMarketValueRaw": {"value": 260000, "currency": "EUR"}, "fieldTranslations": {"nameTranslation": {"ar": "دورجي مارينكوفيتش"}, "shortNameTranslation": {"ar": "د. مارينكوفيتش"}}}, "teamId": 25733, "shirtNumber": 15, "jerseyNumber": "15", "position": "M", "substitute": true, "statistics": {"totalPass": 15, "accuratePass": 13, "totalLongBalls": 2, "accurateLongBalls": 1, "goalAssist": 0, "accurateOwnHalfPasses": 8, "totalOwnHalfPasses": 9, "accurateOppositionHalfPasses": 5, "totalOppositionHalfPasses": 6, "aerialLost": 1, "duelLost": 1, "duelWon": 1, "ballRecovery": 3, "totalTackle": 1, "wonTackle": 1, "minutesPlayed": 45, "touches": 17, "rating": 6.6, "possessionLostCtrl": 2, "ratingVersions": {"original": 6.6, "alternative": 6.7}, "totalShots": 0, "passValueNormalized": -0.09, "dribbleValueNormalized": 0.11, "defensiveValueNormalized": 0.14, "statisticsType": {"sportSlug": "football", "statisticsType": "player"}}}, {"player": {"name": "Nikola Boranijašević", "firstName": "", "lastName": "", "slug": "nikola-boranijasevic", "shortName": "N. Boranijašević", "position": "D", "jerseyNumber": "28", "height": 180, "userCount": 43, "gender": "M", "country": {"alpha2": "RS", "alpha3": "SRB", "name": "Serbia", "slug": "serbia"}, "id": 150667, "marketValueCurrency": "EUR", "dateOfBirthTimestamp": 706233600, "proposedMarketValueRaw": {"value": 165000, "currency": "EUR"}, "fieldTranslations": {"nameTranslation": {"ar": "نيكولا بورانياسيفيتش", "bn": "নিকোলা বোরানিজাসেভিচ", "hi": "निकोला बोरानिजासेविक"}, "shortNameTranslation": {"ar": "ن. بورانياسيفيتش", "bn": "এন. বোরানিজাসেভিচ", "hi": "एन. बोरानिजासेविक"}}}, "teamId": 7771, "shirtNumber": 28, "jerseyNumber": "28", "position": "D", "substitute": true, "statistics": {"totalPass": 21, "accuratePass": 14, "totalLongBalls": 5, "accurateLongBalls": 3, "goalAssist": 0, "accurateOwnHalfPasses": 11, "totalOwnHalfPasses": 16, "accurateOppositionHalfPasses": 3, "totalOppositionHalfPasses": 5, "aerialLost": 1, "aerialWon": 2, "duelLost": 3, "duelWon": 3, "totalClearance": 3, "ballRecovery": 3, "unsuccessfulTouch": 2, "wasFouled": 1, "fouls": 3, "minutesPlayed": 45, "touches": 34, "rating": 6.9, "possessionLostCtrl": 10, "keyPass": 1, "ratingVersions": {"original": 6.9, "alternative": 6.7}, "totalShots": 0, "passValueNormalized": 0.08, "dribbleValueNormalized": 0.09, "defensiveValueNormalized": -0.03, "statisticsType": {"sportSlug": "football", "statisticsType": "player"}}}, {"player": {"name": "Miloš Mijić", "firstName": "", "lastName": "", "slug": "milos-mijic", "shortName": "M. Mijić", "position": "M", "jerseyNumber": "14", "height": 175, "userCount": 11, "gender": "M", "country": {"alpha2": "RS", "alpha3": "SRB", "name": "Serbia", "slug": "serbia"}, "id": 177037, "marketValueCurrency": "EUR", "dateOfBirthTimestamp": 627696000, "proposedMarketValueRaw": {"value": 52000, "currency": "EUR"}, "fieldTranslations": {"nameTranslation": {"ar": "ميلوش ميجيش", "bn": "মিলোস মিজিচ", "hi": "मिलोस मिजिक"}, "shortNameTranslation": {"ar": "م. ميجيش", "bn": "এম. মিজিচ", "hi": "एम. मिजिक"}}}, "teamId": 5160, "shirtNumber": 14, "jerseyNumber": "14", "position": "M", "substitute": true, "statistics": {"totalPass": 7, "accuratePass": 3, "goalAssist": 0, "accurateOwnHalfPasses": 2, "totalOwnHalfPasses": 4, "accurateOppositionHalfPasses": 1, "totalOppositionHalfPasses": 3, "duelWon": 1, "bigChanceMissed": 1, "onTargetScoringAttempt": 1, "ballRecovery": 3, "totalTackle": 1, "wonTackle": 1, "minutesPlayed": 8, "touches": 9, "rating": 5.8, "possessionLostCtrl": 4, "penaltyMiss": 1, "ratingVersions": {"original": 5.8, "alternative": 5.9}, "totalShots": 1, "shotValueNormalized": -0.89, "passValueNormalized": 0.02, "dribbleValueNormalized": 0, "defensiveValueNormalized": -0.1, "statisticsType": {"sportSlug": "football", "statisticsType": "player"}}}, {"player": {"name": "Mihailo Todosijevic", "firstName": "Mihailo Todosijevic", "slug": "mihailo-todosijevic", "shortName": "M. Todosijevic", "position": "F", "jerseyNumber": "22", "userCount": 19, "gender": "M", "country": {"alpha2": "RS", "alpha3": "SRB", "name": "Serbia", "slug": "serbia"}, "id": 1981982, "marketValueCurrency": "EUR", "dateOfBirthTimestamp": 1196121600, "fieldTranslations": {"nameTranslation": {"ar": "ميهايلو تودوسيفيتش"}, "shortNameTranslation": {"ar": "م. تودوسيفيتش"}}}, "teamId": 7771, "shirtNumber": 22, "jerseyNumber": "22", "position": "D", "substitute": true, "statistics": {"totalShots": 0, "statisticsType": {"sportSlug": "football", "statisticsType": "player"}}}, {"player": {"name": "Bogdan Matijasevic", "firstName": "Bogdan Matijasevic", "slug": "bogdan-matijasevic", "shortName": "B. Matijašević", "position": "G", "jerseyNumber": "23", "height": 195, "userCount": 5, "gender": "M", "country": {"alpha2": "RS", "alpha3": "SRB", "name": "Serbia", "slug": "serbia"}, "id": 1166128, "marketValueCurrency": "EUR", "dateOfBirthTimestamp": 1085616000, "proposedMarketValueRaw": {"value": 46000, "currency": "EUR"}, "fieldTranslations": {"nameTranslation": {"ar": "بوغدان ماتياشيفيتش"}, "shortNameTranslation": {"ar": "ب. ماتياشيفيتش"}}}, "teamId": 7771, "shirtNumber": 23, "jerseyNumber": "23", "position": "G", "substitute": true, "statistics": {"totalShots": 0, "statisticsType": {"sportSlug": "football", "statisticsType": "player"}}}, {"player": {"name": "Filip Žunić", "firstName": "", "lastName": "", "slug": "filip-zunic", "shortName": "F. Žunić", "position": "M", "jerseyNumber": "18", "height": 180, "userCount": 10, "gender": "M", "country": {"alpha2": "RS", "alpha3": "SRB", "name": "Serbia", "slug": "serbia"}, "id": 1030454, "marketValueCurrency": "EUR", "dateOfBirthTimestamp": 1021507200, "proposedMarketValueRaw": {"value": 725000, "currency": "EUR"}, "fieldTranslations": {"nameTranslation": {"ar": "فيليب زونيش"}, "shortNameTranslation": {"ar": "ف. زونيش"}}}, "teamId": 7771, "shirtNumber": 18, "jerseyNumber": "18", "position": "D", "substitute": true, "statistics": {"totalShots": 0, "statisticsType": {"sportSlug": "football", "statisticsType": "player"}}}, {"player": {"name": "David Đokić", "slug": "david-dokic", "shortName": "D. Đokić", "position": "F", "jerseyNumber": "36", "userCount": 26, "gender": "M", "country": {"alpha2": "RS", "alpha3": "SRB", "name": "Serbia", "slug": "serbia"}, "id": 2162392, "marketValueCurrency": "EUR", "dateOfBirthTimestamp": 1247011200, "proposedMarketValueRaw": {"value": 52000, "currency": "EUR"}, "fieldTranslations": {"nameTranslation": {"ar": "ديفيد دوكيتش"}, "shortNameTranslation": {"ar": "د. دوكيتش"}}}, "teamId": 324865, "shirtNumber": 36, "jerseyNumber": "36", "position": "F", "substitute": true, "statistics": {"totalShots": 0, "statisticsType": {"sportSlug": "football", "statisticsType": "player"}}}, {"player": {"name": "Aleksa Milošević", "firstName": "Aleksa Milosevic", "slug": "aleksa-milosevic", "shortName": "A. Milošević", "position": "D", "jerseyNumber": "20", "height": 183, "userCount": 22, "gender": "M", "country": {"alpha2": "RS", "alpha3": "SRB", "name": "Serbia", "slug": "serbia"}, "id": 1859501, "marketValueCurrency": "EUR", "dateOfBirthTimestamp": 1168214400, "proposedMarketValueRaw": {"value": 260000, "currency": "EUR"}, "fieldTranslations": {"nameTranslation": {"ar": "أليكس ميلوشيفيتش"}, "shortNameTranslation": {"ar": "أ. ميلوشيفيتش"}}}, "teamId": 7771, "shirtNumber": 20, "jerseyNumber": "20", "position": "D", "substitute": true, "statistics": {"totalShots": 0, "statisticsType": {"sportSlug": "football", "statisticsType": "player"}}}, {"player": {"name": "Milan Joksimović", "firstName": "", "lastName": "", "slug": "milan-joksimovic", "shortName": "M. Joksimović", "position": "D", "jerseyNumber": "12", "height": 184, "userCount": 6, "gender": "M", "country": {"alpha2": "RS", "alpha3": "SRB", "name": "Serbia", "slug": "serbia"}, "id": 111313, "marketValueCurrency": "EUR", "dateOfBirthTimestamp": 634521600, "proposedMarketValueRaw": {"value": 110000, "currency": "EUR"}, "fieldTranslations": {"nameTranslation": {"ar": "ميلان يوكسيموفيتش"}, "shortNameTranslation": {"ar": "م. يوكسيموفيتش"}}}, "teamId": 7771, "shirtNumber": 12, "jerseyNumber": "12", "position": "D", "substitute": true, "statistics": {"totalShots": 0, "statisticsType": {"sportSlug": "football", "statisticsType": "player"}}}], "supportStaff": [], "formation": "5-3-2", "playerColor": {"primary": "ffffff", "number": "000000", "outline": "ffffff", "fancyNumber": "222226"}, "goalkeeperColor": {"primary": "00ff00", "number": "000000", "outline": "00ff00", "fancyNumber": "222226"}}, "statisticalVersion": 3}