{"confirmed": true, "home": {"players": [{"player": {"name": "Marko Kordić", "firstName": "", "lastName": "", "slug": "marko-kordic", "shortName": "M. Kordić", "position": "G", "jerseyNumber": "25", "height": 186, "userCount": 4, "gender": "M", "country": {"alpha2": "ME", "alpha3": "MNE", "name": "Montenegro", "slug": "montenegro"}, "id": 188987, "marketValueCurrency": "EUR", "dateOfBirthTimestamp": 793411200, "proposedMarketValueRaw": {"value": 335000, "currency": "EUR"}, "fieldTranslations": {"nameTranslation": {"ar": "ماركو كورديتش", "bn": "মার্কো কর্ডিচ", "hi": "मार्को कोर्डिक"}, "shortNameTranslation": {"ar": "م. كورديتش", "bn": "এম. কোর্ডিচ", "hi": "एम. कोर्डिक"}}}, "teamId": 6216, "shirtNumber": 25, "jerseyNumber": "25", "position": "G", "substitute": false, "statistics": {"totalPass": 28, "accuratePass": 27, "totalLongBalls": 10, "accurateLongBalls": 9, "goalAssist": 0, "accurateOwnHalfPasses": 19, "totalOwnHalfPasses": 19, "accurateOppositionHalfPasses": 8, "totalOppositionHalfPasses": 9, "totalCross": 0, "accurateCross": 0, "aerialLost": 0, "aerialWon": 0, "duelLost": 0, "duelWon": 0, "challengeLost": 0, "totalContest": 0, "wonContest": 0, "onTargetScoringAttempt": 0, "goals": 0, "totalClearance": 0, "outfielderBlock": 0, "ballRecovery": 6, "totalTackle": 0, "wonTackle": 0, "errorLeadToAShot": 0, "ownGoals": 0, "unsuccessfulTouch": 0, "wasFouled": 0, "fouls": 0, "totalOffside": 0, "crossNotClaimed": 0, "goodHighClaim": 0, "saves": 1, "totalKeeperSweeper": 2, "accurateKeeperSweeper": 0, "minutesPlayed": 90, "touches": 32, "rating": 6.8, "possessionLostCtrl": 3, "expectedGoals": 0, "expectedAssists": 0, "ratingVersions": {"original": 6.8, "alternative": null}, "totalShots": 0, "statisticsType": {"sportSlug": "football", "statisticsType": "player"}}}, {"player": {"name": "Marko Roganović", "firstName": "", "lastName": "", "slug": "marko-roganovic", "shortName": "M. Roganović", "position": "D", "height": 184, "userCount": 8, "gender": "M", "country": {"alpha2": "ME", "alpha3": "MNE", "name": "Montenegro", "slug": "montenegro"}, "id": 101141, "marketValueCurrency": "EUR", "dateOfBirthTimestamp": 835315200, "proposedMarketValueRaw": {"value": 140000, "currency": "EUR"}, "fieldTranslations": {"nameTranslation": {"ar": "ماركو روجانوفيتش", "bn": "মার্কো রোগানোভিচ", "hi": "मार्को रोगानोविक"}, "shortNameTranslation": {"ar": "م. روجانوفيتش", "bn": "এম. রোগানোভিচ", "hi": "एम. रोगानोविक"}}}, "teamId": 6216, "shirtNumber": 99, "jerseyNumber": "99", "position": "D", "substitute": false, "statistics": {"totalPass": 23, "accuratePass": 17, "totalLongBalls": 7, "accurateLongBalls": 3, "goalAssist": 0, "accurateOwnHalfPasses": 9, "totalOwnHalfPasses": 10, "accurateOppositionHalfPasses": 6, "totalOppositionHalfPasses": 11, "totalCross": 1, "accurateCross": 1, "aerialLost": 0, "aerialWon": 1, "duelLost": 5, "duelWon": 8, "challengeLost": 2, "totalContest": 3, "wonContest": 3, "onTargetScoringAttempt": 0, "goals": 0, "totalClearance": 2, "outfielderBlock": 0, "interceptionWon": 1, "ballRecovery": 8, "totalTackle": 0, "wonTackle": 0, "errorLeadToAShot": 0, "ownGoals": 0, "unsuccessfulTouch": 0, "wasFouled": 2, "fouls": 3, "totalOffside": 0, "minutesPlayed": 59, "touches": 32, "rating": 6.8, "possessionLostCtrl": 9, "expectedGoals": 0, "expectedAssists": 0.23, "keyPass": 1, "ratingVersions": {"original": 6.8, "alternative": null}, "totalShots": 0, "statisticsType": {"sportSlug": "football", "statisticsType": "player"}}}, {"player": {"name": "Aleksandar Kapisoda", "slug": "aleksandar-kapisoda", "shortName": "A. Kapisoda", "position": "D", "jerseyNumber": "5", "height": 189, "userCount": 2, "gender": "M", "country": {"alpha2": "ME", "alpha3": "MNE", "name": "Montenegro", "slug": "montenegro"}, "id": 55534, "marketValueCurrency": "EUR", "dateOfBirthTimestamp": 621993600, "proposedMarketValueRaw": {"value": 23000, "currency": "EUR"}, "fieldTranslations": {"nameTranslation": {"ar": "ألكسندر كابيسودا"}, "shortNameTranslation": {"ar": "أ. كابيسودا"}}}, "teamId": 6216, "shirtNumber": 5, "jerseyNumber": "5", "position": "D", "substitute": false, "statistics": {"totalPass": 31, "accuratePass": 27, "totalLongBalls": 2, "accurateLongBalls": 1, "goalAssist": 0, "accurateOwnHalfPasses": 22, "totalOwnHalfPasses": 25, "accurateOppositionHalfPasses": 5, "totalOppositionHalfPasses": 6, "totalCross": 0, "accurateCross": 0, "aerialLost": 0, "aerialWon": 4, "duelLost": 4, "duelWon": 6, "challengeLost": 2, "totalContest": 0, "wonContest": 0, "onTargetScoringAttempt": 0, "goals": 0, "totalClearance": 2, "outfielderBlock": 0, "interceptionWon": 2, "ballRecovery": 15, "totalTackle": 3, "wonTackle": 1, "errorLeadToAShot": 1, "ownGoals": 0, "unsuccessfulTouch": 0, "wasFouled": 0, "fouls": 0, "totalOffside": 0, "minutesPlayed": 90, "touches": 34, "rating": 6.6, "possessionLostCtrl": 7, "expectedGoals": 0, "expectedAssists": 0, "ratingVersions": {"original": 6.6, "alternative": null}, "totalShots": 0, "statisticsType": {"sportSlug": "football", "statisticsType": "player"}}}, {"player": {"name": "Marko Merdović", "firstName": "", "lastName": "", "slug": "merdovic-marko", "shortName": "M. Merdović", "position": "D", "jerseyNumber": "44", "height": 190, "userCount": 11, "gender": "M", "country": {"alpha2": "ME", "alpha3": "MNE", "name": "Montenegro", "slug": "montenegro"}, "id": 986362, "marketValueCurrency": "EUR", "dateOfBirthTimestamp": 911260800, "proposedMarketValueRaw": {"value": 230000, "currency": "EUR"}, "fieldTranslations": {"nameTranslation": {"ar": "ميردوفيتش، ماركو", "bn": "মারডোভিচ, মার্ক", "hi": "मेरडोविक, मार्को"}, "shortNameTranslation": {"ar": "م. ميردوفيتش", "bn": "এম. মারডোভিচ", "hi": "एम. मेरडोविक"}}}, "teamId": 6216, "shirtNumber": 44, "jerseyNumber": "44", "position": "D", "substitute": false, "statistics": {"totalPass": 58, "accuratePass": 48, "totalLongBalls": 11, "accurateLongBalls": 7, "goalAssist": 0, "accurateOwnHalfPasses": 40, "totalOwnHalfPasses": 44, "accurateOppositionHalfPasses": 7, "totalOppositionHalfPasses": 13, "totalCross": 0, "accurateCross": 0, "aerialLost": 0, "aerialWon": 3, "duelLost": 2, "duelWon": 4, "challengeLost": 0, "totalContest": 0, "wonContest": 0, "onTargetScoringAttempt": 0, "goals": 0, "totalClearance": 5, "outfielderBlock": 1, "interceptionWon": 2, "ballRecovery": 14, "totalTackle": 0, "wonTackle": 0, "errorLeadToAShot": 0, "ownGoals": 0, "unsuccessfulTouch": 0, "wasFouled": 1, "fouls": 0, "totalOffside": 0, "minutesPlayed": 90, "touches": 67, "rating": 7.1, "possessionLostCtrl": 14, "expectedGoals": 0, "expectedAssists": 0, "ratingVersions": {"original": 7.1, "alternative": null}, "totalShots": 0, "statisticsType": {"sportSlug": "football", "statisticsType": "player"}}}, {"player": {"name": "Dejan Boljević", "slug": "dejan-boljevic", "shortName": "D. Boljević", "position": "D", "jerseyNumber": "33", "height": 183, "userCount": 3, "gender": "M", "country": {"alpha2": "ME", "alpha3": "MNE", "name": "Montenegro", "slug": "montenegro"}, "id": 57339, "marketValueCurrency": "EUR", "dateOfBirthTimestamp": 644025600, "proposedMarketValueRaw": {"value": 94000, "currency": "EUR"}, "fieldTranslations": {"nameTranslation": {"ar": "ديان بوليفيتش", "bn": "দেজান বলজেভিচ", "hi": "देजान बोलजेविक"}, "shortNameTranslation": {"ar": "د. بوليفيتش", "bn": "ডি. বলজেভিচ", "hi": "डी. बोलजेविक"}}}, "teamId": 6216, "shirtNumber": 33, "jerseyNumber": "33", "position": "D", "substitute": false, "captain": true, "statistics": {"totalPass": 32, "accuratePass": 25, "totalLongBalls": 7, "accurateLongBalls": 3, "goalAssist": 1, "accurateOwnHalfPasses": 11, "totalOwnHalfPasses": 12, "accurateOppositionHalfPasses": 14, "totalOppositionHalfPasses": 20, "totalCross": 3, "accurateCross": 2, "aerialLost": 0, "aerialWon": 1, "duelLost": 5, "duelWon": 7, "challengeLost": 2, "totalContest": 0, "wonContest": 0, "onTargetScoringAttempt": 0, "goals": 0, "totalClearance": 2, "outfielderBlock": 0, "ballRecovery": 9, "totalTackle": 0, "wonTackle": 0, "errorLeadToAShot": 0, "ownGoals": 0, "unsuccessfulTouch": 1, "wasFouled": 4, "fouls": 2, "totalOffside": 0, "minutesPlayed": 90, "touches": 47, "rating": 7.1, "possessionLostCtrl": 17, "expectedGoals": 0, "expectedAssists": 0.19, "keyPass": 1, "ratingVersions": {"original": 7.1, "alternative": null}, "totalShots": 0, "statisticsType": {"sportSlug": "football", "statisticsType": "player"}}}, {"player": {"name": "Stefan Fićović", "slug": "stefan-ficovic", "shortName": "S. Fićović", "position": "M", "jerseyNumber": "18", "height": 183, "userCount": 9, "gender": "M", "country": {"alpha2": "RS", "alpha3": "SRB", "name": "Serbia", "slug": "serbia"}, "id": 889063, "marketValueCurrency": "EUR", "dateOfBirthTimestamp": 896572800, "proposedMarketValueRaw": {"value": 315000, "currency": "EUR"}, "fieldTranslations": {"nameTranslation": {"ar": "ستيفان فيتشوفيتش"}, "shortNameTranslation": {"ar": "س. فيتشوفيتش"}}}, "teamId": 6216, "shirtNumber": 18, "jerseyNumber": "18", "position": "M", "substitute": false, "statistics": {"totalPass": 34, "accuratePass": 22, "totalLongBalls": 2, "accurateLongBalls": 1, "goalAssist": 0, "accurateOwnHalfPasses": 12, "totalOwnHalfPasses": 16, "accurateOppositionHalfPasses": 8, "totalOppositionHalfPasses": 16, "totalCross": 1, "accurateCross": 0, "aerialLost": 4, "aerialWon": 1, "duelLost": 16, "duelWon": 5, "challengeLost": 3, "dispossessed": 1, "totalContest": 5, "wonContest": 4, "onTargetScoringAttempt": 0, "goals": 0, "totalClearance": 1, "outfielderBlock": 0, "interceptionWon": 2, "ballRecovery": 5, "totalTackle": 1, "wonTackle": 0, "errorLeadToAShot": 0, "ownGoals": 0, "unsuccessfulTouch": 0, "wasFouled": 0, "fouls": 1, "totalOffside": 0, "minutesPlayed": 90, "touches": 48, "rating": 6.5, "possessionLostCtrl": 15, "expectedGoals": 0, "expectedAssists": 0, "keyPass": 1, "ratingVersions": {"original": 6.5, "alternative": null}, "totalShots": 0, "statisticsType": {"sportSlug": "football", "statisticsType": "player"}}}, {"player": {"name": "Nikola Balević", "slug": "nikola-balevic", "shortName": "N. Balević", "position": "M", "userCount": 4, "gender": "M", "country": {"alpha2": "ME", "alpha3": "MNE", "name": "Montenegro", "slug": "montenegro"}, "id": 1606688, "marketValueCurrency": "EUR", "dateOfBirthTimestamp": 1198454400, "fieldTranslations": {"nameTranslation": {"ar": "نيكولا باليفيتش"}, "shortNameTranslation": {"ar": "ن. باليفيتش"}}}, "teamId": 241802, "shirtNumber": 14, "jerseyNumber": "14", "position": "M", "substitute": false, "statistics": {"totalPass": 33, "accuratePass": 27, "totalLongBalls": 7, "accurateLongBalls": 2, "goalAssist": 0, "accurateOwnHalfPasses": 17, "totalOwnHalfPasses": 18, "accurateOppositionHalfPasses": 9, "totalOppositionHalfPasses": 14, "totalCross": 0, "accurateCross": 0, "aerialLost": 2, "aerialWon": 3, "duelLost": 7, "duelWon": 8, "challengeLost": 1, "totalContest": 1, "wonContest": 1, "onTargetScoringAttempt": 1, "goals": 0, "totalClearance": 1, "outfielderBlock": 0, "interceptionWon": 2, "ballRecovery": 13, "totalTackle": 1, "wonTackle": 0, "errorLeadToAShot": 0, "ownGoals": 0, "unsuccessfulTouch": 0, "wasFouled": 0, "fouls": 3, "totalOffside": 0, "minutesPlayed": 85, "touches": 39, "rating": 7, "possessionLostCtrl": 10, "expectedGoals": 0.05, "expectedAssists": 0.04, "keyPass": 1, "ratingVersions": {"original": 7, "alternative": null}, "totalShots": 1, "statisticsType": {"sportSlug": "football", "statisticsType": "player"}}}, {"player": {"name": "Nemanja Carević", "firstName": "Nemanja Carevic", "lastName": "", "slug": "nemanja-carevic", "shortName": "N. Carević", "position": "M", "jerseyNumber": "21", "height": 185, "userCount": 8, "gender": "M", "country": {"alpha2": "ME", "alpha3": "MNE", "name": "Montenegro", "slug": "montenegro"}, "id": 1381384, "marketValueCurrency": "EUR", "dateOfBirthTimestamp": 1081382400, "proposedMarketValueRaw": {"value": 205000, "currency": "EUR"}, "fieldTranslations": {"nameTranslation": {"ar": "نيمانجا كاريتش"}, "shortNameTranslation": {"ar": "ن. كاريتش"}}}, "teamId": 6216, "shirtNumber": 21, "jerseyNumber": "21", "position": "M", "substitute": false, "statistics": {"totalPass": 22, "accuratePass": 13, "totalLongBalls": 0, "accurateLongBalls": 0, "goalAssist": 0, "accurateOwnHalfPasses": 11, "totalOwnHalfPasses": 16, "accurateOppositionHalfPasses": 1, "totalOppositionHalfPasses": 5, "totalCross": 1, "accurateCross": 0, "aerialLost": 2, "aerialWon": 1, "duelLost": 12, "duelWon": 7, "challengeLost": 0, "dispossessed": 1, "totalContest": 2, "wonContest": 1, "onTargetScoringAttempt": 2, "blockedScoringAttempt": 1, "goals": 1, "totalClearance": 3, "outfielderBlock": 0, "ballRecovery": 7, "totalTackle": 2, "wonTackle": 1, "errorLeadToAShot": 0, "ownGoals": 0, "unsuccessfulTouch": 0, "wasFouled": 2, "fouls": 1, "totalOffside": 0, "minutesPlayed": 90, "touches": 40, "rating": 7.2, "possessionLostCtrl": 13, "expectedGoals": 0.48, "expectedAssists": 0, "ratingVersions": {"original": 7.2, "alternative": null}, "totalShots": 3, "statisticsType": {"sportSlug": "football", "statisticsType": "player"}}}, {"player": {"name": "Žarko Popović", "firstName": "", "lastName": "", "slug": "zarko-popovic", "shortName": "Ž. Popović", "position": "M", "jerseyNumber": "4", "height": 175, "userCount": 6, "gender": "M", "country": {"alpha2": "ME", "alpha3": "MNE", "name": "Montenegro", "slug": "montenegro"}, "id": 1030468, "marketValueCurrency": "EUR", "dateOfBirthTimestamp": 939600000, "proposedMarketValueRaw": {"value": 255000, "currency": "EUR"}, "fieldTranslations": {"nameTranslation": {"ar": "زاركو بوبوفيتش"}, "shortNameTranslation": {"ar": "ز. بوبوفيتش"}}}, "teamId": 6216, "shirtNumber": 4, "jerseyNumber": "4", "position": "M", "substitute": false, "statistics": {"totalPass": 24, "accuratePass": 19, "totalLongBalls": 1, "accurateLongBalls": 1, "goalAssist": 0, "accurateOwnHalfPasses": 12, "totalOwnHalfPasses": 14, "accurateOppositionHalfPasses": 7, "totalOppositionHalfPasses": 10, "totalCross": 1, "accurateCross": 0, "aerialLost": 2, "aerialWon": 0, "duelLost": 15, "duelWon": 7, "challengeLost": 2, "dispossessed": 1, "totalContest": 2, "wonContest": 2, "shotOffTarget": 1, "onTargetScoringAttempt": 0, "blockedScoringAttempt": 2, "goals": 0, "totalClearance": 0, "outfielderBlock": 0, "ballRecovery": 3, "totalTackle": 0, "wonTackle": 0, "errorLeadToAShot": 0, "ownGoals": 0, "unsuccessfulTouch": 0, "wasFouled": 3, "fouls": 3, "totalOffside": 0, "minutesPlayed": 85, "touches": 49, "rating": 6.3, "possessionLostCtrl": 11, "expectedGoals": 0.11, "expectedAssists": 0, "ratingVersions": {"original": 6.3, "alternative": null}, "totalShots": 3, "statisticsType": {"sportSlug": "football", "statisticsType": "player"}}}, {"player": {"name": "Nemanja Belaković", "firstName": "", "lastName": "", "slug": "nemanja-belakovic", "shortName": "N. Belaković", "position": "F", "jerseyNumber": "8", "height": 183, "userCount": 33, "gender": "M", "country": {"alpha2": "RS", "alpha3": "SRB", "name": "Serbia", "slug": "serbia"}, "id": 979046, "marketValueCurrency": "EUR", "dateOfBirthTimestamp": 852681600, "proposedMarketValueRaw": {"value": 470000, "currency": "EUR"}, "fieldTranslations": {"nameTranslation": {"ar": "نيمانجا بيلاكوفيتش"}, "shortNameTranslation": {"ar": "ن. بيلاكوفيتش"}}}, "teamId": 6216, "shirtNumber": 11, "jerseyNumber": "11", "position": "M", "substitute": false, "statistics": {"totalPass": 29, "accuratePass": 19, "totalLongBalls": 5, "accurateLongBalls": 1, "goalAssist": 1, "accurateOwnHalfPasses": 11, "totalOwnHalfPasses": 14, "accurateOppositionHalfPasses": 7, "totalOppositionHalfPasses": 14, "totalCross": 2, "accurateCross": 1, "aerialLost": 0, "aerialWon": 5, "duelLost": 12, "duelWon": 11, "challengeLost": 0, "totalContest": 3, "wonContest": 2, "onTargetScoringAttempt": 0, "goals": 0, "totalClearance": 2, "outfielderBlock": 0, "interceptionWon": 2, "ballRecovery": 16, "totalTackle": 0, "wonTackle": 0, "errorLeadToAShot": 0, "ownGoals": 0, "unsuccessfulTouch": 0, "wasFouled": 5, "fouls": 0, "totalOffside": 1, "minutesPlayed": 90, "touches": 45, "rating": 7.2, "possessionLostCtrl": 22, "expectedGoals": 0, "expectedAssists": 0.24, "keyPass": 1, "ratingVersions": {"original": 7.2, "alternative": null}, "totalShots": 0, "statisticsType": {"sportSlug": "football", "statisticsType": "player"}}}, {"player": {"name": "Boban Đorđević", "slug": "boban-dordevic", "shortName": "B. Đorđević", "position": "F", "height": 188, "userCount": 14, "gender": "M", "country": {"alpha2": "ME", "alpha3": "MNE", "name": "Montenegro", "slug": "montenegro"}, "id": 1164363, "marketValueCurrency": "EUR", "dateOfBirthTimestamp": 856396800, "proposedMarketValueRaw": {"value": 190000, "currency": "EUR"}, "fieldTranslations": {"nameTranslation": {"ar": "بوبان دورديفيتش"}, "shortNameTranslation": {"ar": "ب. دورديفيتش"}}}, "teamId": 6216, "shirtNumber": 9, "jerseyNumber": "9", "position": "F", "substitute": false, "statistics": {"totalPass": 9, "accuratePass": 7, "totalLongBalls": 0, "accurateLongBalls": 0, "goalAssist": 0, "accurateOwnHalfPasses": 2, "totalOwnHalfPasses": 3, "accurateOppositionHalfPasses": 5, "totalOppositionHalfPasses": 6, "totalCross": 0, "accurateCross": 0, "aerialLost": 6, "aerialWon": 2, "duelLost": 12, "duelWon": 4, "challengeLost": 0, "dispossessed": 1, "totalContest": 0, "wonContest": 0, "onTargetScoringAttempt": 0, "goals": 0, "totalClearance": 0, "outfielderBlock": 0, "ballRecovery": 1, "totalTackle": 0, "wonTackle": 0, "errorLeadToAShot": 0, "ownGoals": 0, "unsuccessfulTouch": 0, "wasFouled": 1, "fouls": 0, "totalOffside": 0, "minutesPlayed": 55, "touches": 18, "rating": 6.4, "possessionLostCtrl": 11, "expectedGoals": 0, "expectedAssists": 0, "ratingVersions": {"original": 6.4, "alternative": null}, "totalShots": 0, "statisticsType": {"sportSlug": "football", "statisticsType": "player"}}}, {"player": {"name": "Savo Arambašić", "slug": "savo-arambasic", "shortName": "S. Arambašić", "position": "M", "jerseyNumber": "17", "height": 183, "userCount": 27, "gender": "M", "country": {"alpha2": "RS", "alpha3": "SRB", "name": "Serbia", "slug": "serbia"}, "id": 1046042, "marketValueCurrency": "EUR", "dateOfBirthTimestamp": 980553600, "proposedMarketValueRaw": {"value": 290000, "currency": "EUR"}, "fieldTranslations": {"nameTranslation": {"ar": "سافو أرامباشيتش"}, "shortNameTranslation": {"ar": "س. أرامباشيتش"}}}, "teamId": 6216, "shirtNumber": 17, "jerseyNumber": "17", "position": "F", "substitute": true, "statistics": {"totalPass": 7, "accuratePass": 4, "totalLongBalls": 1, "accurateLongBalls": 0, "goalAssist": 0, "accurateOwnHalfPasses": 2, "totalOwnHalfPasses": 3, "accurateOppositionHalfPasses": 2, "totalOppositionHalfPasses": 4, "totalCross": 0, "accurateCross": 0, "aerialLost": 1, "aerialWon": 1, "duelLost": 5, "duelWon": 4, "challengeLost": 0, "dispossessed": 1, "totalContest": 1, "wonContest": 0, "onTargetScoringAttempt": 0, "goals": 0, "totalClearance": 0, "outfielderBlock": 0, "ballRecovery": 4, "totalTackle": 0, "wonTackle": 0, "errorLeadToAShot": 0, "ownGoals": 0, "unsuccessfulTouch": 0, "wasFouled": 0, "fouls": 0, "totalOffside": 1, "minutesPlayed": 35, "touches": 16, "rating": 6.4, "possessionLostCtrl": 6, "expectedGoals": 0, "expectedAssists": 0, "ratingVersions": {"original": 6.4, "alternative": null}, "totalShots": 0, "statisticsType": {"sportSlug": "football", "statisticsType": "player"}}}, {"player": {"name": "Vladan Kordić", "firstName": "", "lastName": "", "slug": "vladan-kordic", "shortName": "V. Kordić", "position": "F", "jerseyNumber": "98", "height": 178, "userCount": 8, "gender": "M", "country": {"alpha2": "ME", "alpha3": "MNE", "name": "Montenegro", "slug": "montenegro"}, "id": 959868, "marketValueCurrency": "EUR", "dateOfBirthTimestamp": 898473600, "proposedMarketValueRaw": {"value": 52000, "currency": "EUR"}, "fieldTranslations": {"nameTranslation": {"ar": "فلادان كوردتش"}, "shortNameTranslation": {"ar": "ف. كوردتش"}}}, "teamId": 6216, "shirtNumber": 98, "jerseyNumber": "98", "position": "F", "substitute": true, "statistics": {"totalPass": 5, "accuratePass": 4, "totalLongBalls": 0, "accurateLongBalls": 0, "goalAssist": 0, "accurateOwnHalfPasses": 2, "totalOwnHalfPasses": 3, "accurateOppositionHalfPasses": 2, "totalOppositionHalfPasses": 2, "totalCross": 0, "accurateCross": 0, "aerialLost": 1, "aerialWon": 0, "duelLost": 4, "duelWon": 1, "challengeLost": 0, "totalContest": 0, "wonContest": 0, "onTargetScoringAttempt": 1, "goals": 1, "totalClearance": 0, "outfielderBlock": 0, "ballRecovery": 1, "totalTackle": 0, "wonTackle": 0, "errorLeadToAShot": 0, "ownGoals": 0, "unsuccessfulTouch": 0, "wasFouled": 1, "fouls": 1, "totalOffside": 1, "minutesPlayed": 31, "touches": 8, "rating": 7.2, "possessionLostCtrl": 1, "expectedGoals": 0.19, "expectedAssists": 0.01, "keyPass": 1, "ratingVersions": {"original": 7.2, "alternative": null}, "totalShots": 1, "statisticsType": {"sportSlug": "football", "statisticsType": "player"}}}, {"player": {"name": "Marko Franeta", "slug": "marko-franeta", "shortName": "M. Franeta", "position": "D", "jerseyNumber": "13", "height": 192, "userCount": 18, "gender": "M", "country": {"alpha2": "ME", "alpha3": "MNE", "name": "Montenegro", "slug": "montenegro"}, "id": 1484679, "marketValueCurrency": "EUR", "dateOfBirthTimestamp": 1102809600, "proposedMarketValueRaw": {"value": 245000, "currency": "EUR"}, "fieldTranslations": {"nameTranslation": {"ar": "ماركو فرانيتا"}, "shortNameTranslation": {"ar": "م. فرانيتا"}}}, "teamId": 6216, "shirtNumber": 13, "jerseyNumber": "13", "position": "D", "substitute": true, "statistics": {"totalPass": 0, "accuratePass": 0, "totalLongBalls": 0, "accurateLongBalls": 0, "goalAssist": 0, "totalCross": 0, "accurateCross": 0, "aerialLost": 0, "aerialWon": 0, "duelLost": 0, "duelWon": 0, "challengeLost": 0, "totalContest": 0, "wonContest": 0, "onTargetScoringAttempt": 0, "goals": 0, "totalClearance": 0, "outfielderBlock": 0, "ballRecovery": 0, "totalTackle": 0, "wonTackle": 0, "errorLeadToAShot": 0, "ownGoals": 0, "unsuccessfulTouch": 0, "wasFouled": 0, "fouls": 0, "totalOffside": 0, "minutesPlayed": 5, "rating": 6.3, "possessionLostCtrl": 1, "expectedGoals": 0, "expectedAssists": 0, "ratingVersions": {"original": 6.3, "alternative": null}, "totalShots": 0, "statisticsType": {"sportSlug": "football", "statisticsType": "player"}}}, {"player": {"name": "Strahinja Tešović", "firstName": "Strahinja Tesovic", "slug": "strahinja-tesovic", "shortName": "S. Tešović", "position": "M", "jerseyNumber": "32", "height": 179, "userCount": 67, "gender": "M", "country": {"alpha2": "ME", "alpha3": "MNE", "name": "Montenegro", "slug": "montenegro"}, "id": 1218114, "marketValueCurrency": "EUR", "dateOfBirthTimestamp": 1104883200, "fieldTranslations": {"nameTranslation": {"ar": "ستراهيجنا تيشوفيتش"}, "shortNameTranslation": {"ar": "س. تيشوفيتش"}}}, "teamId": 6216, "shirtNumber": 32, "jerseyNumber": "32", "position": "F", "substitute": true, "statistics": {"totalPass": 2, "accuratePass": 1, "totalLongBalls": 0, "accurateLongBalls": 0, "goalAssist": 0, "totalOwnHalfPasses": 1, "totalCross": 0, "accurateCross": 0, "aerialLost": 1, "aerialWon": 0, "duelLost": 1, "duelWon": 2, "challengeLost": 0, "totalContest": 1, "wonContest": 1, "onTargetScoringAttempt": 1, "goals": 1, "totalClearance": 1, "outfielderBlock": 0, "ballRecovery": 3, "totalTackle": 0, "wonTackle": 0, "errorLeadToAShot": 0, "ownGoals": 0, "unsuccessfulTouch": 0, "wasFouled": 0, "fouls": 0, "totalOffside": 0, "minutesPlayed": 5, "touches": 5, "rating": 7.5, "possessionLostCtrl": 3, "expectedGoals": 0.14, "expectedAssists": 0, "ratingVersions": {"original": 7.5, "alternative": null}, "totalShots": 1, "statisticsType": {"sportSlug": "football", "statisticsType": "player"}}}, {"player": {"name": "Suad Ličina", "firstName": "", "lastName": "", "slug": "suad-licina", "shortName": "S. Ličina", "position": "G", "jerseyNumber": "1", "height": 195, "userCount": 14, "gender": "M", "country": {"alpha2": "ME", "alpha3": "MNE", "name": "Montenegro", "slug": "montenegro"}, "id": 355010, "marketValueCurrency": "EUR", "dateOfBirthTimestamp": 792201600, "proposedMarketValueRaw": {"value": 46000, "currency": "EUR"}, "fieldTranslations": {"nameTranslation": {"ar": "سواد ليشينا", "bn": "সুআদ লিচিনা", "hi": "सुआद लिचिना"}, "shortNameTranslation": {"ar": "س. ليشينا", "bn": "এস. লিচিনা", "hi": "सी. लिचिना"}}}, "teamId": 6216, "shirtNumber": 1, "jerseyNumber": "1", "position": "G", "substitute": true}, {"player": {"name": "Janko Vukićević", "firstName": "Janko", "lastName": "Vukićević", "slug": "janko-vukicevic", "shortName": "J. Vukićević", "position": "D", "userCount": 6, "gender": "M", "country": {"alpha2": "ME", "alpha3": "MNE", "name": "Montenegro", "slug": "montenegro"}, "id": 1149277, "marketValueCurrency": "EUR", "dateOfBirthTimestamp": 1111968000, "fieldTranslations": {"nameTranslation": {"ar": "يانكو فوكيتشيفيتش"}, "shortNameTranslation": {"ar": "ي. فوكيتشيفيتش"}}}, "teamId": 43979, "shirtNumber": 19, "jerseyNumber": "19", "position": "D", "substitute": true}, {"player": {"name": "Đorđe Fabris", "slug": "dorde-fabris", "shortName": "Đ. Fabris", "position": "D", "jerseyNumber": "27", "userCount": 5, "gender": "M", "country": {"alpha2": "ME", "alpha3": "MNE", "name": "Montenegro", "slug": "montenegro"}, "id": 1976042, "marketValueCurrency": "EUR", "dateOfBirthTimestamp": 1213056000, "fieldTranslations": {"nameTranslation": {"ar": "دورجي فابريس"}, "shortNameTranslation": {"ar": "د. فابريس"}}}, "teamId": 22631, "shirtNumber": 27, "jerseyNumber": "27", "position": "D", "substitute": true}, {"player": {"name": "Luka Bastrica", "firstName": "Luka Bastrica", "slug": "luka-bastrica", "shortName": "L. Bastrica", "position": "M", "userCount": 1, "gender": "M", "country": {"alpha2": "ME", "alpha3": "MNE", "name": "Montenegro", "slug": "montenegro"}, "id": 1981847, "marketValueCurrency": "EUR", "dateOfBirthTimestamp": 1174694400, "fieldTranslations": {"nameTranslation": {"ar": "لوكا باستريكا"}, "shortNameTranslation": {"ar": "ل. باستريكا"}}}, "teamId": 241802, "shirtNumber": 45, "jerseyNumber": "45", "position": "M", "substitute": true}, {"player": {"name": "Nikola Zvrko", "firstName": "", "lastName": "", "slug": "nikola-zvrko", "shortName": "N. Zvrko", "position": "M", "jerseyNumber": "7", "height": 180, "userCount": 6, "gender": "M", "country": {"alpha2": "RS", "alpha3": "SRB", "name": "Serbia", "slug": "serbia"}, "id": 800100, "marketValueCurrency": "EUR", "dateOfBirthTimestamp": 794534400, "proposedMarketValueRaw": {"value": 140000, "currency": "EUR"}, "fieldTranslations": {"nameTranslation": {"ar": "نيكولا زفركو"}, "shortNameTranslation": {"ar": "ن. زفركو"}}}, "teamId": 6216, "shirtNumber": 7, "jerseyNumber": "7", "position": "M", "substitute": true}], "supportStaff": [], "formation": "4-2-3-1", "playerColor": {"primary": "6699ff", "number": "ffffff", "outline": "6699ff", "fancyNumber": "ffffff"}, "goalkeeperColor": {"primary": "fafb00", "number": "000000", "outline": "fafb00", "fancyNumber": "222226"}}, "away": {"players": [{"player": {"name": "Balša  Radanović", "firstName": "Balša ", "lastName": "Radanović", "slug": "balsa-radanovic", "shortName": "B. Radanović", "position": "G", "jerseyNumber": "31", "userCount": 12, "gender": "M", "country": {"alpha2": "ME", "alpha3": "MNE", "name": "Montenegro", "slug": "montenegro"}, "id": 1648525, "marketValueCurrency": "EUR", "dateOfBirthTimestamp": 1178064000, "fieldTranslations": {"nameTranslation": {"ar": "بالشا رادانوفيتش"}, "shortNameTranslation": {"ar": "ب. رادانوفيتش"}}}, "teamId": 327162, "shirtNumber": 31, "jerseyNumber": "31", "position": "G", "substitute": false, "statistics": {"totalPass": 19, "accuratePass": 13, "totalLongBalls": 11, "accurateLongBalls": 6, "goalAssist": 0, "accurateOwnHalfPasses": 9, "totalOwnHalfPasses": 11, "accurateOppositionHalfPasses": 4, "totalOppositionHalfPasses": 8, "totalCross": 0, "accurateCross": 0, "aerialLost": 0, "aerialWon": 0, "duelLost": 0, "duelWon": 0, "challengeLost": 0, "totalContest": 0, "wonContest": 0, "onTargetScoringAttempt": 0, "goals": 0, "totalClearance": 0, "outfielderBlock": 0, "ballRecovery": 1, "totalTackle": 0, "wonTackle": 0, "errorLeadToAShot": 0, "ownGoals": 0, "unsuccessfulTouch": 0, "wasFouled": 0, "fouls": 0, "totalOffside": 0, "crossNotClaimed": 0, "goodHighClaim": 0, "savedShotsFromInsideTheBox": 1, "saves": 2, "totalKeeperSweeper": 0, "accurateKeeperSweeper": 0, "minutesPlayed": 90, "touches": 23, "rating": 6, "possessionLostCtrl": 7, "expectedGoals": 0, "expectedAssists": 0, "ratingVersions": {"original": 6, "alternative": null}, "totalShots": 0, "statisticsType": {"sportSlug": "football", "statisticsType": "player"}}}, {"player": {"name": "Vuko Vicković", "firstName": "", "lastName": "", "slug": "vuko-vickovic", "shortName": "V. Vicković", "position": "D", "jerseyNumber": "18", "height": 175, "userCount": 7, "gender": "M", "country": {"alpha2": "ME", "alpha3": "MNE", "name": "Montenegro", "slug": "montenegro"}, "id": 1391910, "marketValueCurrency": "EUR", "dateOfBirthTimestamp": 1076284800, "fieldTranslations": {"nameTranslation": {"ar": "فوكو فيكوفيتش"}, "shortNameTranslation": {"ar": "ف. فيكوفيتش"}}}, "teamId": 327162, "shirtNumber": 18, "jerseyNumber": "18", "position": "D", "substitute": false, "statistics": {"totalPass": 27, "accuratePass": 16, "totalLongBalls": 5, "accurateLongBalls": 1, "goalAssist": 0, "accurateOwnHalfPasses": 13, "totalOwnHalfPasses": 15, "accurateOppositionHalfPasses": 3, "totalOppositionHalfPasses": 11, "totalCross": 2, "accurateCross": 0, "aerialLost": 1, "aerialWon": 1, "duelLost": 11, "duelWon": 4, "challengeLost": 3, "totalContest": 0, "wonContest": 0, "shotOffTarget": 1, "onTargetScoringAttempt": 0, "goals": 0, "totalClearance": 0, "outfielderBlock": 0, "ballRecovery": 8, "totalTackle": 0, "wonTackle": 0, "errorLeadToAShot": 0, "ownGoals": 0, "unsuccessfulTouch": 0, "wasFouled": 0, "fouls": 1, "totalOffside": 0, "minutesPlayed": 90, "touches": 30, "rating": 5.8, "possessionLostCtrl": 14, "expectedGoals": 0.01, "expectedAssists": 0, "ratingVersions": {"original": 5.8, "alternative": null}, "totalShots": 1, "statisticsType": {"sportSlug": "football", "statisticsType": "player"}}}, {"player": {"name": "Ljubomir Pejović", "firstName": "Ljubomir", "lastName": "Pejović", "slug": "ljubomir-pejovic", "shortName": "L. Pejović", "position": "D", "jerseyNumber": "37", "height": 190, "userCount": 25, "gender": "M", "country": {"alpha2": "ME", "alpha3": "MNE", "name": "Montenegro", "slug": "montenegro"}, "id": 1005585, "marketValueCurrency": "EUR", "dateOfBirthTimestamp": 1053907200, "proposedMarketValueRaw": {"value": 110000, "currency": "EUR"}, "fieldTranslations": {"nameTranslation": {"ar": "ليوبومير بيجوفيتش"}, "shortNameTranslation": {"ar": "ل. بيجوفيتش"}}}, "teamId": 327162, "shirtNumber": 37, "jerseyNumber": "37", "position": "D", "substitute": false, "statistics": {"totalPass": 43, "accuratePass": 33, "totalLongBalls": 10, "accurateLongBalls": 3, "goalAssist": 0, "accurateOwnHalfPasses": 24, "totalOwnHalfPasses": 26, "accurateOppositionHalfPasses": 8, "totalOppositionHalfPasses": 16, "totalCross": 0, "accurateCross": 0, "aerialLost": 2, "aerialWon": 1, "duelLost": 8, "duelWon": 5, "challengeLost": 2, "totalContest": 0, "wonContest": 0, "onTargetScoringAttempt": 1, "goals": 1, "totalClearance": 4, "outfielderBlock": 0, "interceptionWon": 1, "ballRecovery": 11, "totalTackle": 1, "wonTackle": 1, "errorLeadToAShot": 0, "ownGoals": 0, "unsuccessfulTouch": 0, "wasFouled": 0, "fouls": 1, "totalOffside": 0, "minutesPlayed": 80, "touches": 52, "rating": 7.2, "possessionLostCtrl": 11, "expectedGoals": 0.35, "expectedAssists": 0.01, "keyPass": 1, "ratingVersions": {"original": 7.2, "alternative": null}, "totalShots": 1, "statisticsType": {"sportSlug": "football", "statisticsType": "player"}}}, {"player": {"name": "Luka Uskoković", "slug": "luka-uskokovic", "shortName": "L. Uskoković", "position": "D", "jerseyNumber": "4", "height": 193, "userCount": 28, "gender": "M", "country": {"alpha2": "ME", "alpha3": "MNE", "name": "Montenegro", "slug": "montenegro"}, "id": 605370, "marketValueCurrency": "EUR", "dateOfBirthTimestamp": 829094400, "proposedMarketValueRaw": {"value": 260000, "currency": "EUR"}, "fieldTranslations": {"nameTranslation": {"ar": "لوكا أوسكوكوفيتش", "bn": "লুকা উস্কোকোভিচ", "hi": "लुका उसकोकोविच"}, "shortNameTranslation": {"ar": "ل. أوسكوكوفيتش", "bn": "এল. উস্কোকোভিচ", "hi": "एल. उसकोकोविच"}}}, "teamId": 327162, "shirtNumber": 4, "jerseyNumber": "4", "position": "D", "substitute": false, "statistics": {"totalPass": 49, "accuratePass": 43, "totalLongBalls": 14, "accurateLongBalls": 9, "goalAssist": 0, "accurateOwnHalfPasses": 30, "totalOwnHalfPasses": 30, "accurateOppositionHalfPasses": 12, "totalOppositionHalfPasses": 18, "totalCross": 0, "accurateCross": 0, "aerialLost": 2, "aerialWon": 3, "duelLost": 7, "duelWon": 6, "challengeLost": 2, "totalContest": 0, "wonContest": 0, "onTargetScoringAttempt": 0, "goals": 0, "totalClearance": 2, "outfielderBlock": 1, "interceptionWon": 2, "ballRecovery": 21, "totalTackle": 0, "wonTackle": 0, "errorLeadToAShot": 1, "ownGoals": 0, "unsuccessfulTouch": 0, "wasFouled": 0, "fouls": 0, "totalOffside": 0, "minutesPlayed": 90, "touches": 60, "rating": 6.6, "possessionLostCtrl": 7, "expectedGoals": 0, "expectedAssists": 0, "ratingVersions": {"original": 6.6, "alternative": null}, "totalShots": 0, "statisticsType": {"sportSlug": "football", "statisticsType": "player"}}}, {"player": {"name": "Zvonko Ceklić", "slug": "zvonko-ceklic", "shortName": "Z. Ceklić", "position": "D", "jerseyNumber": "6", "height": 190, "userCount": 2, "gender": "M", "country": {"alpha2": "ME", "alpha3": "MNE", "name": "Montenegro", "slug": "montenegro"}, "id": 880655, "marketValueCurrency": "EUR", "dateOfBirthTimestamp": 923788800, "proposedMarketValueRaw": {"value": 26000, "currency": "EUR"}, "fieldTranslations": {"nameTranslation": {"ar": "زفونكو سيكليتش", "bn": "জোনকো সেক্লিচ", "hi": "ज़्वोन्को सेक्लिक"}, "shortNameTranslation": {"ar": "ز. سيكليتش", "bn": "জেড. সেক্লিচ", "hi": "ज़ेड. सेक्लिक"}}}, "teamId": 327162, "shirtNumber": 6, "jerseyNumber": "6", "position": "D", "substitute": false, "statistics": {"totalPass": 31, "accuratePass": 23, "totalLongBalls": 3, "accurateLongBalls": 2, "goalAssist": 0, "accurateOwnHalfPasses": 15, "totalOwnHalfPasses": 18, "accurateOppositionHalfPasses": 8, "totalOppositionHalfPasses": 13, "totalCross": 0, "accurateCross": 0, "aerialLost": 0, "aerialWon": 3, "duelLost": 11, "duelWon": 4, "challengeLost": 1, "totalContest": 1, "wonContest": 0, "bigChanceMissed": 1, "shotOffTarget": 1, "onTargetScoringAttempt": 0, "goals": 0, "totalClearance": 2, "outfielderBlock": 1, "interceptionWon": 1, "ballRecovery": 11, "totalTackle": 0, "wonTackle": 0, "errorLeadToAShot": 0, "ownGoals": 0, "unsuccessfulTouch": 3, "wasFouled": 0, "fouls": 2, "totalOffside": 0, "minutesPlayed": 90, "touches": 49, "rating": 6.1, "possessionLostCtrl": 16, "expectedGoals": 0.55, "expectedAssists": 0, "ratingVersions": {"original": 6.1, "alternative": null}, "totalShots": 1, "statisticsType": {"sportSlug": "football", "statisticsType": "player"}}}, {"player": {"name": "Nelson Augustin Cordoba", "firstName": "", "lastName": "", "slug": "nelson-augustin-cordoba", "shortName": "N. A. Cordoba", "position": "M", "jerseyNumber": "28", "height": 177, "userCount": 13, "gender": "M", "country": {"alpha2": "AR", "alpha3": "ARG", "name": "Argentina", "slug": "argentina"}, "id": 1163021, "marketValueCurrency": "EUR", "dateOfBirthTimestamp": 925516800, "proposedMarketValueRaw": {"value": 91000, "currency": "EUR"}, "fieldTranslations": {"nameTranslation": {"ar": "نيلسون أوغستين كوردوبا"}, "shortNameTranslation": {"ar": "ن. كوردوبا"}}}, "teamId": 327162, "shirtNumber": 28, "jerseyNumber": "28", "position": "M", "substitute": false, "statistics": {"totalPass": 40, "accuratePass": 36, "totalLongBalls": 4, "accurateLongBalls": 3, "goalAssist": 1, "accurateOwnHalfPasses": 27, "totalOwnHalfPasses": 29, "accurateOppositionHalfPasses": 9, "totalOppositionHalfPasses": 11, "totalCross": 0, "accurateCross": 0, "aerialLost": 2, "aerialWon": 2, "duelLost": 11, "duelWon": 5, "challengeLost": 1, "totalContest": 2, "wonContest": 2, "bigChanceCreated": 1, "onTargetScoringAttempt": 0, "goals": 0, "totalClearance": 3, "outfielderBlock": 0, "interceptionWon": 1, "ballRecovery": 9, "totalTackle": 3, "wonTackle": 0, "errorLeadToAShot": 0, "ownGoals": 0, "unsuccessfulTouch": 0, "wasFouled": 2, "fouls": 2, "totalOffside": 0, "minutesPlayed": 90, "touches": 53, "rating": 7.1, "possessionLostCtrl": 11, "expectedGoals": 0, "expectedAssists": 0.35, "keyPass": 1, "ratingVersions": {"original": 7.1, "alternative": null}, "totalShots": 0, "statisticsType": {"sportSlug": "football", "statisticsType": "player"}}}, {"player": {"name": "Nikola Radusinović", "firstName": "Nikola", "lastName": "Radusinović", "slug": "nikola-radusinovic", "shortName": "N. Radusinović", "position": "M", "jerseyNumber": "16", "height": 187, "userCount": 3, "gender": "M", "country": {"alpha2": "ME", "alpha3": "MNE", "name": "Montenegro", "slug": "montenegro"}, "id": 1149286, "marketValueCurrency": "EUR", "dateOfBirthTimestamp": 1111190400, "proposedMarketValueRaw": {"value": 52000, "currency": "EUR"}, "fieldTranslations": {"nameTranslation": {"ar": "نيكولا رادوسينوفيتش"}, "shortNameTranslation": {"ar": "ن. رادوسينوفيتش"}}}, "teamId": 327162, "shirtNumber": 16, "jerseyNumber": "16", "position": "M", "substitute": false, "statistics": {"totalPass": 18, "accuratePass": 16, "totalLongBalls": 1, "accurateLongBalls": 1, "goalAssist": 0, "accurateOwnHalfPasses": 7, "totalOwnHalfPasses": 8, "accurateOppositionHalfPasses": 9, "totalOppositionHalfPasses": 10, "totalCross": 0, "accurateCross": 0, "aerialLost": 3, "aerialWon": 1, "duelLost": 12, "duelWon": 2, "challengeLost": 1, "dispossessed": 1, "totalContest": 0, "wonContest": 0, "onTargetScoringAttempt": 0, "goals": 0, "totalClearance": 1, "outfielderBlock": 1, "ballRecovery": 4, "totalTackle": 1, "wonTackle": 0, "errorLeadToAShot": 0, "ownGoals": 0, "unsuccessfulTouch": 0, "wasFouled": 1, "fouls": 3, "totalOffside": 0, "minutesPlayed": 83, "touches": 28, "rating": 6.3, "possessionLostCtrl": 9, "expectedGoals": 0, "expectedAssists": 0, "ratingVersions": {"original": 6.3, "alternative": null}, "totalShots": 0, "statisticsType": {"sportSlug": "football", "statisticsType": "player"}}}, {"player": {"name": "Mamadou Camara", "firstName": "", "lastName": "", "slug": "mamadou-camara", "shortName": "M. Camara", "position": "M", "jerseyNumber": "78", "height": 185, "userCount": 110, "gender": "M", "country": {"alpha2": "SN", "alpha3": "SEN", "name": "Senegal", "slug": "senegal"}, "id": 1134549, "marketValueCurrency": "EUR", "dateOfBirthTimestamp": 1034640000, "proposedMarketValueRaw": {"value": 195000, "currency": "EUR"}, "fieldTranslations": {"nameTranslation": {"ar": "مامادو كامارا", "bn": "মামাদু কামারা", "hi": "मामादौ कैमारा"}, "shortNameTranslation": {"ar": "م. كامارا", "bn": "এম. কামারা", "hi": "एम. कैमारा"}}}, "teamId": 315641, "shirtNumber": 78, "jerseyNumber": "78", "position": "M", "substitute": false, "statistics": {"totalPass": 40, "accuratePass": 34, "totalLongBalls": 3, "accurateLongBalls": 0, "goalAssist": 0, "accurateOwnHalfPasses": 20, "totalOwnHalfPasses": 21, "accurateOppositionHalfPasses": 13, "totalOppositionHalfPasses": 18, "totalCross": 0, "accurateCross": 0, "aerialLost": 1, "aerialWon": 1, "duelLost": 10, "duelWon": 6, "challengeLost": 2, "totalContest": 2, "wonContest": 2, "onTargetScoringAttempt": 0, "goals": 0, "totalClearance": 1, "outfielderBlock": 0, "interceptionWon": 1, "ballRecovery": 12, "totalTackle": 2, "wonTackle": 0, "errorLeadToAShot": 0, "ownGoals": 0, "unsuccessfulTouch": 0, "wasFouled": 2, "fouls": 1, "totalOffside": 0, "minutesPlayed": 75, "touches": 52, "rating": 6.9, "possessionLostCtrl": 4, "expectedGoals": 0, "expectedAssists": 0, "ratingVersions": {"original": 6.9, "alternative": null}, "totalShots": 0, "statisticsType": {"sportSlug": "football", "statisticsType": "player"}}}, {"player": {"name": "Stephano Almeida", "firstName": "Stephano", "lastName": "Almeida", "slug": "stephano-almeida", "shortName": "S. Almeida", "position": "M", "jerseyNumber": "27", "height": 180, "userCount": 13, "gender": "M", "country": {"alpha2": "BR", "alpha3": "BRA", "name": "Brazil", "slug": "brazil"}, "id": 978475, "marketValueCurrency": "EUR", "dateOfBirthTimestamp": 748224000, "proposedMarketValueRaw": {"value": 165000, "currency": "EUR"}, "fieldTranslations": {"nameTranslation": {"ar": "ستيفانو ألميدا", "bn": "স্টেফানো নাউমোভস্কি", "hi": "स्टेफानो अल्मेडा"}, "shortNameTranslation": {"ar": "س. ألميدا", "bn": "এস. নাউমোভস্কি", "hi": "एस. अल्मेडा"}}}, "teamId": 327162, "shirtNumber": 27, "jerseyNumber": "27", "position": "F", "substitute": false, "statistics": {"totalPass": 12, "accuratePass": 8, "totalLongBalls": 0, "accurateLongBalls": 0, "goalAssist": 0, "accurateOwnHalfPasses": 2, "totalOwnHalfPasses": 3, "accurateOppositionHalfPasses": 5, "totalOppositionHalfPasses": 7, "totalCross": 1, "accurateCross": 0, "aerialLost": 5, "aerialWon": 0, "duelLost": 15, "duelWon": 5, "challengeLost": 1, "dispossessed": 1, "totalContest": 4, "wonContest": 3, "onTargetScoringAttempt": 1, "blockedScoringAttempt": 1, "goals": 0, "totalClearance": 0, "outfielderBlock": 0, "interceptionWon": 1, "ballRecovery": 1, "totalTackle": 0, "wonTackle": 0, "errorLeadToAShot": 0, "ownGoals": 0, "unsuccessfulTouch": 1, "wasFouled": 2, "fouls": 5, "totalOffside": 2, "minutesPlayed": 83, "touches": 32, "rating": 6.9, "possessionLostCtrl": 12, "expectedGoals": 0.09, "expectedAssists": 0.55, "keyPass": 2, "ratingVersions": {"original": 6.9, "alternative": null}, "totalShots": 2, "statisticsType": {"sportSlug": "football", "statisticsType": "player"}}}, {"player": {"name": "Jagoš Roganović", "slug": "jagos-roganovic", "shortName": "J. Roganović", "position": "F", "jerseyNumber": "29", "height": 187, "userCount": 8, "gender": "M", "country": {"alpha2": "ME", "alpha3": "MNE", "name": "Montenegro", "slug": "montenegro"}, "id": 1620437, "marketValueCurrency": "EUR", "dateOfBirthTimestamp": 1168214400, "proposedMarketValueRaw": {"value": 49000, "currency": "EUR"}, "fieldTranslations": {"nameTranslation": {"ar": "ياجوش روجانوفيتش"}, "shortNameTranslation": {"ar": "ي. روجانوفيتش"}}}, "teamId": 327162, "shirtNumber": 29, "jerseyNumber": "29", "position": "F", "substitute": false, "statistics": {"totalPass": 15, "accuratePass": 13, "totalLongBalls": 0, "accurateLongBalls": 0, "goalAssist": 0, "accurateOwnHalfPasses": 6, "totalOwnHalfPasses": 7, "accurateOppositionHalfPasses": 7, "totalOppositionHalfPasses": 8, "totalCross": 0, "accurateCross": 0, "aerialLost": 2, "aerialWon": 0, "duelLost": 8, "duelWon": 2, "challengeLost": 0, "dispossessed": 3, "totalContest": 0, "wonContest": 0, "onTargetScoringAttempt": 0, "goals": 0, "totalClearance": 0, "outfielderBlock": 0, "ballRecovery": 2, "totalTackle": 0, "wonTackle": 0, "errorLeadToAShot": 0, "ownGoals": 0, "unsuccessfulTouch": 0, "wasFouled": 0, "fouls": 0, "totalOffside": 0, "minutesPlayed": 75, "touches": 24, "rating": 6.4, "possessionLostCtrl": 6, "expectedGoals": 0, "expectedAssists": 0, "ratingVersions": {"original": 6.4, "alternative": null}, "totalShots": 0, "statisticsType": {"sportSlug": "football", "statisticsType": "player"}}}, {"player": {"name": "Lazar Knezevic", "firstName": "Lazar Knezevic", "slug": "lazar-knezevic", "shortName": "L. Knezevic", "position": "M", "jerseyNumber": "7", "height": 190, "userCount": 5, "gender": "M", "country": {"alpha2": "ME", "alpha3": "MNE", "name": "Montenegro", "slug": "montenegro"}, "id": 1497156, "marketValueCurrency": "EUR", "dateOfBirthTimestamp": 1098576000, "proposedMarketValueRaw": {"value": 93000, "currency": "EUR"}, "fieldTranslations": {"nameTranslation": {"ar": "لازار كنيزيفيتش"}, "shortNameTranslation": {"ar": "ل. كنيزيفيتش"}}}, "teamId": 327162, "shirtNumber": 7, "jerseyNumber": "7", "position": "F", "substitute": false, "statistics": {"totalPass": 16, "accuratePass": 8, "totalLongBalls": 1, "accurateLongBalls": 1, "goalAssist": 0, "accurateOwnHalfPasses": 1, "totalOwnHalfPasses": 4, "accurateOppositionHalfPasses": 7, "totalOppositionHalfPasses": 11, "totalCross": 5, "accurateCross": 2, "aerialLost": 5, "aerialWon": 0, "duelLost": 14, "duelWon": 9, "challengeLost": 0, "dispossessed": 1, "totalContest": 9, "wonContest": 7, "onTargetScoringAttempt": 0, "goals": 0, "totalClearance": 1, "outfielderBlock": 0, "interceptionWon": 1, "ballRecovery": 3, "totalTackle": 0, "wonTackle": 0, "errorLeadToAShot": 1, "ownGoals": 0, "unsuccessfulTouch": 0, "wasFouled": 5, "fouls": 6, "totalOffside": 0, "minutesPlayed": 90, "touches": 38, "rating": 7, "possessionLostCtrl": 13, "expectedGoals": 0, "expectedAssists": 0.13, "keyPass": 1, "ratingVersions": {"original": 7, "alternative": null}, "totalShots": 0, "statisticsType": {"sportSlug": "football", "statisticsType": "player"}}}, {"player": {"name": "Dušan Vuković", "firstName": "", "lastName": "", "slug": "dusan-vukovic", "shortName": "D. Vuković", "position": "M", "jerseyNumber": "77", "userCount": 23, "gender": "M", "country": {"alpha2": "ME", "alpha3": "MNE", "name": "Montenegro", "slug": "montenegro"}, "id": 1103884, "marketValueCurrency": "EUR", "dateOfBirthTimestamp": 1059264000, "proposedMarketValueRaw": {"value": 135000, "currency": "EUR"}, "fieldTranslations": {"nameTranslation": {"ar": "دوشان فوكوفيتش"}, "shortNameTranslation": {"ar": "د. فوكوفيتش"}}}, "teamId": 327162, "shirtNumber": 77, "jerseyNumber": "77", "position": "M", "substitute": true, "statistics": {"totalPass": 3, "accuratePass": 2, "totalLongBalls": 1, "accurateLongBalls": 0, "goalAssist": 0, "accurateOwnHalfPasses": 1, "totalOwnHalfPasses": 1, "accurateOppositionHalfPasses": 1, "totalOppositionHalfPasses": 2, "totalCross": 0, "accurateCross": 0, "aerialLost": 2, "aerialWon": 0, "duelLost": 5, "duelWon": 2, "challengeLost": 0, "dispossessed": 2, "totalContest": 1, "wonContest": 1, "onTargetScoringAttempt": 0, "goals": 0, "totalClearance": 0, "outfielderBlock": 0, "ballRecovery": 2, "totalTackle": 0, "wonTackle": 0, "errorLeadToAShot": 0, "ownGoals": 0, "unsuccessfulTouch": 0, "wasFouled": 0, "fouls": 0, "totalOffside": 0, "minutesPlayed": 15, "touches": 9, "rating": 6.1, "possessionLostCtrl": 3, "expectedGoals": 0, "expectedAssists": 0, "ratingVersions": {"original": 6.1, "alternative": null}, "totalShots": 0, "statisticsType": {"sportSlug": "football", "statisticsType": "player"}}}, {"player": {"name": "Rodrigo Faust", "slug": "rodrigo-faust", "shortName": "R. Faust", "position": "F", "jerseyNumber": "9", "height": 184, "userCount": 8, "gender": "M", "country": {"alpha2": "AR", "alpha3": "ARG", "name": "Argentina", "slug": "argentina"}, "id": 871881, "marketValueCurrency": "EUR", "dateOfBirthTimestamp": 811036800, "proposedMarketValueRaw": {"value": 185000, "currency": "EUR"}, "fieldTranslations": {"nameTranslation": {"ar": "رودريغو فاوست"}, "shortNameTranslation": {"ar": "ر. فاوست"}}}, "teamId": 327162, "shirtNumber": 9, "jerseyNumber": "9", "position": "F", "substitute": true, "statistics": {"totalPass": 7, "accuratePass": 5, "totalLongBalls": 0, "accurateLongBalls": 0, "goalAssist": 0, "accurateOwnHalfPasses": 3, "totalOwnHalfPasses": 3, "accurateOppositionHalfPasses": 2, "totalOppositionHalfPasses": 4, "totalCross": 1, "accurateCross": 0, "aerialLost": 1, "aerialWon": 0, "duelLost": 3, "duelWon": 1, "challengeLost": 0, "totalContest": 1, "wonContest": 1, "onTargetScoringAttempt": 0, "goals": 0, "totalClearance": 0, "outfielderBlock": 0, "ballRecovery": 0, "totalTackle": 0, "wonTackle": 0, "errorLeadToAShot": 0, "ownGoals": 0, "unsuccessfulTouch": 0, "wasFouled": 0, "fouls": 1, "totalOffside": 0, "minutesPlayed": 15, "touches": 10, "rating": 6.5, "possessionLostCtrl": 3, "expectedGoals": 0, "expectedAssists": 0, "ratingVersions": {"original": 6.5, "alternative": null}, "totalShots": 0, "statisticsType": {"sportSlug": "football", "statisticsType": "player"}}}, {"player": {"name": "Matije Badnjar", "firstName": "Matije Badnjar", "slug": "matije-badnjar", "shortName": "M. Badnjar", "position": "D", "jerseyNumber": "3", "height": 177, "userCount": 4, "gender": "M", "country": {"alpha2": "ME", "alpha3": "MNE", "name": "Montenegro", "slug": "montenegro"}, "id": 1381381, "marketValueCurrency": "EUR", "dateOfBirthTimestamp": 1117670400, "proposedMarketValueRaw": {"value": 49000, "currency": "EUR"}, "fieldTranslations": {"nameTranslation": {"ar": "ماتييه بادنجار"}, "shortNameTranslation": {"ar": "م. بادنجار"}}}, "teamId": 327162, "shirtNumber": 3, "jerseyNumber": "3", "position": "D", "substitute": true, "statistics": {"totalPass": 3, "accuratePass": 3, "totalLongBalls": 0, "accurateLongBalls": 0, "goalAssist": 0, "accurateOppositionHalfPasses": 3, "totalOppositionHalfPasses": 3, "totalCross": 0, "accurateCross": 0, "aerialLost": 1, "aerialWon": 1, "duelLost": 3, "duelWon": 1, "challengeLost": 0, "totalContest": 0, "wonContest": 0, "onTargetScoringAttempt": 0, "goals": 0, "totalClearance": 0, "outfielderBlock": 0, "ballRecovery": 1, "totalTackle": 0, "wonTackle": 0, "errorLeadToAShot": 1, "ownGoals": 0, "unsuccessfulTouch": 0, "wasFouled": 0, "fouls": 0, "totalOffside": 0, "minutesPlayed": 10, "touches": 4, "rating": 6, "possessionLostCtrl": 4, "expectedGoals": 0, "expectedAssists": 0, "ratingVersions": {"original": 6, "alternative": null}, "totalShots": 0, "statisticsType": {"sportSlug": "football", "statisticsType": "player"}}}, {"player": {"name": "Veljko Mijović", "firstName": "Veljko", "lastName": "Mijović", "slug": "veljko-mijovic", "shortName": "V. Mijović", "position": "M", "userCount": 3, "gender": "M", "country": {"alpha2": "ME", "alpha3": "MNE", "name": "Montenegro", "slug": "montenegro"}, "id": 2487213, "marketValueCurrency": "EUR", "dateOfBirthTimestamp": 1216166400}, "teamId": 241802, "shirtNumber": 35, "jerseyNumber": "35", "position": "M", "substitute": true, "statistics": {"totalPass": 3, "accuratePass": 3, "totalLongBalls": 0, "accurateLongBalls": 0, "goalAssist": 0, "accurateOppositionHalfPasses": 3, "totalOppositionHalfPasses": 3, "totalCross": 0, "accurateCross": 0, "aerialLost": 0, "aerialWon": 0, "duelLost": 0, "duelWon": 0, "challengeLost": 0, "totalContest": 0, "wonContest": 0, "onTargetScoringAttempt": 0, "goals": 0, "totalClearance": 0, "outfielderBlock": 0, "ballRecovery": 1, "totalTackle": 0, "wonTackle": 0, "errorLeadToAShot": 0, "ownGoals": 0, "unsuccessfulTouch": 0, "wasFouled": 0, "fouls": 0, "totalOffside": 0, "minutesPlayed": 7, "touches": 3, "rating": 6.5, "possessionLostCtrl": 0, "expectedGoals": 0, "expectedAssists": 0, "ratingVersions": {"original": 6.5, "alternative": null}, "totalShots": 0, "statisticsType": {"sportSlug": "football", "statisticsType": "player"}}}, {"player": {"name": "Stefan Mijović", "firstName": "Stefan", "lastName": "Mijović", "slug": "stefan-mijovic", "shortName": "S. Mijović", "position": "F", "height": 181, "userCount": 2, "gender": "M", "country": {"alpha2": "ME", "alpha3": "MNE", "name": "Montenegro", "slug": "montenegro"}, "id": 1096990, "marketValueCurrency": "EUR", "dateOfBirthTimestamp": 1175817600, "fieldTranslations": {"nameTranslation": {"ar": "ستيفان مييوفيتش"}, "shortNameTranslation": {"ar": "س. مييوفيتش"}}}, "teamId": 327162, "shirtNumber": 66, "jerseyNumber": "66", "position": "F", "substitute": true, "statistics": {"totalPass": 2, "accuratePass": 1, "totalLongBalls": 0, "accurateLongBalls": 0, "goalAssist": 0, "totalOppositionHalfPasses": 1, "totalCross": 1, "accurateCross": 0, "aerialLost": 0, "aerialWon": 0, "duelLost": 0, "duelWon": 2, "challengeLost": 0, "totalContest": 1, "wonContest": 1, "shotOffTarget": 1, "onTargetScoringAttempt": 0, "goals": 0, "totalClearance": 0, "outfielderBlock": 0, "ballRecovery": 0, "totalTackle": 0, "wonTackle": 0, "errorLeadToAShot": 0, "ownGoals": 0, "unsuccessfulTouch": 0, "wasFouled": 1, "fouls": 0, "totalOffside": 0, "minutesPlayed": 7, "touches": 5, "rating": 6.8, "possessionLostCtrl": 0, "expectedGoals": 0.13, "expectedAssists": 0, "ratingVersions": {"original": 6.8, "alternative": null}, "totalShots": 1, "statisticsType": {"sportSlug": "football", "statisticsType": "player"}}}, {"player": {"name": "Petar Radulović", "firstName": "", "lastName": "", "slug": "petar-radulovic", "shortName": "P. Radulović", "position": "G", "jerseyNumber": "25", "height": 193, "userCount": 8, "gender": "M", "country": {"alpha2": "ME", "alpha3": "MNE", "name": "Montenegro", "slug": "montenegro"}, "id": 931333, "marketValueCurrency": "EUR", "dateOfBirthTimestamp": 1005350400, "proposedMarketValueRaw": {"value": 48000, "currency": "EUR"}, "fieldTranslations": {"nameTranslation": {"ar": "بيتار رادولوفيتش", "bn": "পেটার রাদুলোভিচ", "hi": "पीटर रडुलोविक"}, "shortNameTranslation": {"ar": "ب. رادولوفيتش", "bn": "পি. রাদুলোভিচ", "hi": "पी. रडुलोविक"}}}, "teamId": 327162, "shirtNumber": 25, "jerseyNumber": "25", "position": "G", "substitute": true}, {"player": {"name": "Matija Vukčević", "firstName": "Matija Vukčević", "lastName": "", "slug": "matija-vukcevic", "shortName": "M. Vukčević", "position": "D", "jerseyNumber": "44", "userCount": 4, "gender": "M", "country": {"alpha2": "ME", "alpha3": "MNE", "name": "Montenegro", "slug": "montenegro"}, "id": 1426667, "marketValueCurrency": "EUR", "dateOfBirthTimestamp": 1071100800, "fieldTranslations": {"nameTranslation": {"ar": "ماتيا فوكشيفيتش"}, "shortNameTranslation": {"ar": "م. فوكشيفيتش"}}}, "teamId": 327162, "shirtNumber": 44, "jerseyNumber": "44", "position": "D", "substitute": true}, {"player": {"name": "Nemanja Pavićević", "firstName": "Nemanja", "lastName": "Pavićević", "slug": "nemanja-pavicevic", "shortName": "N. Pavićević", "position": "M", "jerseyNumber": "17", "height": 180, "userCount": 3, "gender": "M", "country": {"alpha2": "ME", "alpha3": "MNE", "name": "Montenegro", "slug": "montenegro"}, "id": 1978656, "marketValueCurrency": "EUR", "dateOfBirthTimestamp": 1110499200, "fieldTranslations": {"nameTranslation": {"ar": "نيمانجا بافيتشيفيتش"}, "shortNameTranslation": {"ar": "ن. بافيتشيفيتش"}}}, "teamId": 282802, "shirtNumber": 17, "jerseyNumber": "17", "position": "M", "substitute": true}, {"player": {"name": "Nikola Pavličević", "firstName": "Nikola", "lastName": "Pavličević", "slug": "nikola-pavlicevic", "shortName": "N. Pavličević", "position": "M", "jerseyNumber": "18", "userCount": 1, "gender": "M", "country": {"alpha2": "HR", "alpha3": "HRV", "name": "Croatia", "slug": "croatia"}, "id": 1648560, "marketValueCurrency": "EUR", "dateOfBirthTimestamp": 737251200, "fieldTranslations": {"nameTranslation": {"ar": "نيكولا بافليتشيفيتش"}, "shortNameTranslation": {"ar": "ن. بافليتشيفيتش"}}}, "teamId": 35223, "shirtNumber": 11, "jerseyNumber": "11", "position": "M", "substitute": true}], "supportStaff": [], "formation": "4-3-3", "playerColor": {"primary": "000000", "number": "222226", "outline": "808080", "fancyNumber": "222226"}, "goalkeeperColor": {"primary": "000000", "number": "222226", "outline": "808080", "fancyNumber": "222226"}}, "statisticalVersion": 2}